[
  {
    "date": "2026-07-24",
    "away": "San Diego Padres",
    "away_code": "SDP",
    "home": "Atlanta Braves",
    "home_code": "ATL",
    "game_time_utc": "2026-07-23T16:16:00Z",
    "away_pitcher": "German Marquez",
    "away_pitcher_hand": "R",
    "away_pitcher_id": "608566",
    "home_pitcher": "Grant Holmes",
    "home_pitcher_hand": "R",
    "home_pitcher_id": "656550",
    "ml_away": 212,
    "ml_home": -255,
    "spread_away_line": 1.5,
    "spread_away_price": 105,
    "spread_home_line": -1.5,
    "spread_home_price": -118,
    "total_line": 8.0,
    "over_price": -105,
    "under_price": -105,
    "f5_ml_away": 200,
    "f5_ml_home": -260,
    "f5_spread_away_line": 1.5,
    "f5_spread_away_price": -140,
    "f5_spread_home_line": -1.5,
    "f5_spread_home_price": 108,
    "f5_total_line": 4.5,
    "f5_over_price": -104,
    "f5_under_price": -125,
    "tt_away_line": 2.5,
    "tt_away_over_price": -135,
    "tt_away_under_price": 122,
    "tt_home_line": 4.5,
    "tt_home_over_price": -122,
    "tt_home_under_price": 100,
    "f5_tt_away_line": 1.5,
    "f5_tt_away_over_price": 105,
    "f5_tt_away_under_price": -135,
    "f5_tt_home_line": 2.5,
    "f5_tt_home_over_price": -125,
    "f5_tt_home_under_price": -105,
    "pitchers": [
      {
        "name": "Chris Sale",
        "k_line": 7.5,
        "k_over_price": 102,
        "k_under_price": 126,
        "outs_line": 18.5,
        "outs_over_price": 130,
        "outs_under_price": -150,
        "actual_ks": null,
        "actual_outs": null,
        "k_over_hit": null,
        "outs_over_hit": null
      },
      {
        "name": "Griffin Canning",
        "k_line": 4.5,
        "k_over_price": 126,
        "k_under_price": 130,
        "outs_line": null,
        "outs_over_price": null,
        "outs_under_price": null,
        "actual_ks": null,
        "actual_outs": null,
        "k_over_hit": null,
        "outs_over_hit": null
      }
    ],
    "odds_recorded_at": "2026-07-24T09:42:57.916907+00:00",
    "odds_final": true,
    "away_score": null,
    "home_score": null,
    "total_runs": null,
    "home_win": null,
    "over_hit": null,
    "away_f5_score": null,
    "home_f5_score": null,
    "f5_total_runs": null,
    "f5_home_win": null,
    "f5_over_hit": null,
    "f5_spread_away_covered": null,
    "tt_away_over_hit": null,
    "tt_home_over_hit": null,
    "f5_tt_away_over_hit": null,
    "f5_tt_home_over_hit": null,
    "spread_away_covered": null,
    "annotated_at": null
  },
  {
    "date": "2026-07-24",
    "away": "Minnesota Twins",
    "away_code": "MIN",
    "home": "Cleveland Guardians",
    "home_code": "CLE",
    "game_time_utc": "2026-07-23T17:11:00Z",
    "away_pitcher": "Zebby Matthews",
    "away_pitcher_hand": "R",
    "away_pitcher_id": "805673",
    "home_pitcher": "Joey Cantillo",
    "home_pitcher_hand": "L",
    "home_pitcher_id": "676282",
    "ml_away": 120,
    "ml_home": -138,
    "spread_away_line": 1.5,
    "spread_away_price": -188,
    "spread_home_line": -1.5,
    "spread_home_price": 155,
    "total_line": 7.5,
    "over_price": -115,
    "under_price": 100,
    "f5_ml_away": 112,
    "f5_ml_home": -140,
    "f5_spread_away_line": 0.5,
    "f5_spread_away_price": -135,
    "f5_spread_home_line": -0.5,
    "f5_spread_home_price": 104,
    "f5_total_line": 4.5,
    "f5_over_price": 108,
    "f5_under_price": -140,
    "tt_away_line": 3.5,
    "tt_away_over_price": -113,
    "tt_away_under_price": -113,
    "tt_home_line": 3.5,
    "tt_home_over_price": -145,
    "tt_home_under_price": 114,
    "f5_tt_away_line": 1.5,
    "f5_tt_away_over_price": -125,
    "f5_tt_away_under_price": -105,
    "f5_tt_home_line": 1.5,
    "f5_tt_home_over_price": -154,
    "f5_tt_home_under_price": 120,
    "pitchers": [
      {
        "name": "Gavin Williams",
        "k_line": 6.5,
        "k_over_price": -113,
        "k_under_price": -105,
        "outs_line": 17.5,
        "outs_over_price": -149,
        "outs_under_price": 125,
        "actual_ks": null,
        "actual_outs": null,
        "k_over_hit": null,
        "outs_over_hit": null
      },
      {
        "name": "Taj Bradley",
        "k_line": 6.5,
        "k_over_price": 118,
        "k_under_price": -145,
        "outs_line": 17.5,
        "outs_over_price": -144,
        "outs_under_price": 108,
        "actual_ks": null,
        "actual_outs": null,
        "k_over_hit": null,
        "outs_over_hit": null
      }
    ],
    "odds_recorded_at": "2026-07-24T09:42:57.916907+00:00",
    "odds_final": true,
    "away_score": null,
    "home_score": null,
    "total_runs": null,
    "home_win": null,
    "over_hit": null,
    "away_f5_score": null,
    "home_f5_score": null,
    "f5_total_runs": null,
    "f5_home_win": null,
    "f5_over_hit": null,
    "f5_spread_away_covered": null,
    "tt_away_over_hit": null,
    "tt_home_over_hit": null,
    "f5_tt_away_over_hit": null,
    "f5_tt_home_over_hit": null,
    "spread_away_covered": null,
    "annotated_at": null
  },
  {
    "date": "2026-07-24",
    "away": "Tampa Bay Rays",
    "away_code": "TBR",
    "home": "Toronto Blue Jays",
    "home_code": "TOR",
    "game_time_utc": "2026-07-23T19:08:00Z",
    "away_pitcher": "Shane McClanahan",
    "away_pitcher_hand": "L",
    "away_pitcher_id": "663556",
    "home_pitcher": "Trey Yesavage",
    "home_pitcher_hand": "R",
    "home_pitcher_id": "702056",
    "ml_away": -104,
    "ml_home": -110,
    "spread_away_line": -1.5,
    "spread_away_price": 162,
    "spread_home_line": 1.5,
    "spread_home_price": -180,
    "total_line": 8.5,
    "over_price": -110,
    "under_price": -109,
    "f5_ml_away": -112,
    "f5_ml_home": -112,
    "f5_spread_away_line": 0.5,
    "f5_spread_away_price": -156,
    "f5_spread_home_line": -0.5,
    "f5_spread_home_price": 120,
    "f5_total_line": 4.5,
    "f5_over_price": -114,
    "f5_under_price": -114,
    "tt_away_line": 4.5,
    "tt_away_over_price": 114,
    "tt_away_under_price": -135,
    "tt_home_line": 4.5,
    "tt_home_over_price": 114,
    "tt_home_under_price": 118,
    "f5_tt_away_line": 2.5,
    "f5_tt_away_over_price": 120,
    "f5_tt_away_under_price": -154,
    "f5_tt_home_line": 2.5,
    "f5_tt_home_over_price": 120,
    "f5_tt_home_under_price": -154,
    "pitchers": [
      {
        "name": "Ian Seymour",
        "k_line": 4.5,
        "k_over_price": -125,
        "k_under_price": 102,
        "outs_line": 15.5,
        "outs_over_price": 119,
        "outs_under_price": -158,
        "actual_ks": null,
        "actual_outs": null,
        "k_over_hit": null,
        "outs_over_hit": null
      },
      {
        "name": "Shane Bieber",
        "k_line": 4.5,
        "k_over_price": 125,
        "k_under_price": -155,
        "outs_line": 16.5,
        "outs_over_price": -112,
        "outs_under_price": -112,
        "actual_ks": null,
        "actual_outs": null,
        "k_over_hit": null,
        "outs_over_hit": null
      }
    ],
    "odds_recorded_at": "2026-07-24T09:42:57.916907+00:00",
    "odds_final": true,
    "away_score": null,
    "home_score": null,
    "total_runs": null,
    "home_win": null,
    "over_hit": null,
    "away_f5_score": null,
    "home_f5_score": null,
    "f5_total_runs": null,
    "f5_home_win": null,
    "f5_over_hit": null,
    "f5_spread_away_covered": null,
    "tt_away_over_hit": null,
    "tt_home_over_hit": null,
    "f5_tt_away_over_hit": null,
    "f5_tt_home_over_hit": null,
    "spread_away_covered": null,
    "annotated_at": null
  },
  {
    "date": "2026-07-24",
    "away": "Arizona Diamondbacks",
    "away_code": "ARI",
    "home": "St. Louis Cardinals",
    "home_code": "STL",
    "game_time_utc": "2026-07-23T21:16:00Z",
    "away_pitcher": "E. Rodriguez",
    "away_pitcher_hand": "L",
    "away_pitcher_id": "593958",
    "home_pitcher": "Dustin May",
    "home_pitcher_hand": "R",
    "home_pitcher_id": "669160",
    "ml_away": 102,
    "ml_home": -120,
    "spread_away_line": -1.5,
    "spread_away_price": 168,
    "spread_home_line": -1.5,
    "spread_home_price": 162,
    "total_line": 8.0,
    "over_price": -105,
    "under_price": -110,
    "f5_ml_away": 104,
    "f5_ml_home": -130,
    "f5_spread_away_line": 0.5,
    "f5_spread_away_price": -140,
    "f5_spread_home_line": -0.5,
    "f5_spread_home_price": 108,
    "f5_total_line": 4.5,
    "f5_over_price": -120,
    "f5_under_price": -108,
    "tt_away_line": 3.5,
    "tt_away_over_price": -125,
    "tt_away_under_price": 104,
    "tt_home_line": 3.5,
    "tt_home_over_price": -140,
    "tt_home_under_price": 114,
    "f5_tt_away_line": 1.5,
    "f5_tt_away_over_price": -154,
    "f5_tt_away_under_price": 120,
    "f5_tt_home_line": 2.5,
    "f5_tt_home_over_price": 114,
    "f5_tt_home_under_price": -145,
    "pitchers": [
      {
        "name": "Brandon Pfaadt",
        "k_line": 3.5,
        "k_over_price": 106,
        "k_under_price": -123,
        "outs_line": 16.5,
        "outs_over_price": -114,
        "outs_under_price": -114,
        "actual_ks": null,
        "actual_outs": null,
        "k_over_hit": null,
        "outs_over_hit": null
      },
      {
        "name": "Michael McGreevy",
        "k_line": 3.5,
        "k_over_price": 132,
        "k_under_price": -145,
        "outs_line": 17.5,
        "outs_over_price": -103,
        "outs_under_price": -128,
        "actual_ks": null,
        "actual_outs": null,
        "k_over_hit": null,
        "outs_over_hit": null
      }
    ],
    "odds_recorded_at": "2026-07-24T09:42:57.916907+00:00",
    "odds_final": true,
    "away_score": null,
    "home_score": null,
    "total_runs": null,
    "home_win": null,
    "over_hit": null,
    "away_f5_score": null,
    "home_f5_score": null,
    "f5_total_runs": null,
    "f5_home_win": null,
    "f5_over_hit": null,
    "f5_spread_away_covered": null,
    "tt_away_over_hit": null,
    "tt_home_over_hit": null,
    "f5_tt_away_over_hit": null,
    "f5_tt_home_over_hit": null,
    "spread_away_covered": null,
    "annotated_at": null
  },
  {
    "date": "2026-07-24",
    "away": "Kansas City Royals",
    "away_code": "KCR",
    "home": "Detroit Tigers",
    "home_code": "DET",
    "game_time_utc": "2026-07-23T22:41:00Z",
    "away_pitcher": "Noah Cameron",
    "away_pitcher_hand": "L",
    "away_pitcher_id": "702070",
    "home_pitcher": "Tarik Skubal",
    "home_pitcher_hand": "L",
    "home_pitcher_id": "669373",
    "ml_away": 176,
    "ml_home": -205,
    "spread_away_line": 1.5,
    "spread_away_price": -120,
    "spread_home_line": -1.5,
    "spread_home_price": 105,
    "total_line": 8.5,
    "over_price": -105,
    "under_price": -115,
    "f5_ml_away": 172,
    "f5_ml_home": -220,
    "f5_spread_away_line": 0.5,
    "f5_spread_away_price": 114,
    "f5_spread_home_line": -0.5,
    "f5_spread_home_price": -148,
    "f5_total_line": 4.5,
    "f5_over_price": -114,
    "f5_under_price": -114,
    "tt_away_line": 3.5,
    "tt_away_over_price": 104,
    "tt_away_under_price": -130,
    "tt_home_line": 4.5,
    "tt_home_over_price": -115,
    "tt_home_under_price": -105,
    "f5_tt_away_line": 1.5,
    "f5_tt_away_over_price": -115,
    "f5_tt_away_under_price": -115,
    "f5_tt_home_line": 2.5,
    "f5_tt_home_over_price": -120,
    "f5_tt_home_under_price": -110,
    "pitchers": [
      {
        "name": "Randy Dobnak",
        "k_line": 3.5,
        "k_over_price": 128,
        "k_under_price": -150,
        "outs_line": 14.5,
        "outs_over_price": -154,
        "outs_under_price": 116,
        "actual_ks": null,
        "actual_outs": null,
        "k_over_hit": null,
        "outs_over_hit": null
      },
      {
        "name": "Troy Melton",
        "k_line": 5.5,
        "k_over_price": -104,
        "k_under_price": -120,
        "outs_line": 17.5,
        "outs_over_price": -115,
        "outs_under_price": -104,
        "actual_ks": null,
        "actual_outs": null,
        "k_over_hit": null,
        "outs_over_hit": null
      }
    ],
    "odds_recorded_at": "2026-07-24T09:42:57.916907+00:00",
    "odds_final": true,
    "away_score": null,
    "home_score": null,
    "total_runs": null,
    "home_win": null,
    "over_hit": null,
    "away_f5_score": null,
    "home_f5_score": null,
    "f5_total_runs": null,
    "f5_home_win": null,
    "f5_over_hit": null,
    "f5_spread_away_covered": null,
    "tt_away_over_hit": null,
    "tt_home_over_hit": null,
    "f5_tt_away_over_hit": null,
    "f5_tt_home_over_hit": null,
    "spread_away_covered": null,
    "annotated_at": null
  },
  {
    "date": "2026-07-24",
    "away": "Colorado Rockies",
    "away_code": "COL",
    "home": "Milwaukee Brewers",
    "home_code": "MIL",
    "game_time_utc": "2026-07-24T20:11:00Z",
    "away_pitcher": "Tomoyuki Sugano",
    "away_pitcher_hand": "R",
    "away_pitcher_id": "608372",
    "home_pitcher": "Shane Drohan",
    "home_pitcher_hand": "L",
    "home_pitcher_id": "675660",
    "ml_away": 208,
    "ml_home": -245,
    "spread_away_line": 1.5,
    "spread_away_price": -103,
    "spread_home_line": -1.5,
    "spread_home_price": -113,
    "total_line": 8.5,
    "over_price": -110,
    "under_price": -108,
    "f5_ml_away": 185,
    "f5_ml_home": -225,
    "f5_spread_away_line": 0.5,
    "f5_spread_away_price": 116,
    "f5_spread_home_line": -0.5,
    "f5_spread_home_price": -152,
    "f5_total_line": 4.5,
    "f5_over_price": -120,
    "f5_under_price": -108,
    "tt_away_line": 3.5,
    "tt_away_over_price": 114,
    "tt_away_under_price": -140,
    "tt_home_line": 4.5,
    "tt_home_over_price": -136,
    "tt_home_under_price": 114,
    "f5_tt_away_line": 1.5,
    "f5_tt_away_over_price": -115,
    "f5_tt_away_under_price": -115,
    "f5_tt_home_line": 2.5,
    "f5_tt_home_over_price": -135,
    "f5_tt_home_under_price": 105,
    "pitchers": [
      {
        "name": "Shane Drohan",
        "k_line": 5.5,
        "k_over_price": -125,
        "k_under_price": 100,
        "outs_line": 17.5,
        "outs_over_price": -134,
        "outs_under_price": 102,
        "actual_ks": null,
        "actual_outs": null,
        "k_over_hit": null,
        "outs_over_hit": null
      },
      {
        "name": "Tomoyuki Sugano",
        "k_line": 3.5,
        "k_over_price": 106,
        "k_under_price": -135,
        "outs_line": 15.5,
        "outs_over_price": 113,
        "outs_under_price": -148,
        "actual_ks": null,
        "actual_outs": null,
        "k_over_hit": null,
        "outs_over_hit": null
      }
    ],
    "odds_recorded_at": "2026-07-24T09:42:57.916907+00:00",
    "odds_final": false,
    "away_score": null,
    "home_score": null,
    "total_runs": null,
    "home_win": null,
    "over_hit": null,
    "away_f5_score": null,
    "home_f5_score": null,
    "f5_total_runs": null,
    "f5_home_win": null,
    "f5_over_hit": null,
    "f5_spread_away_covered": null,
    "tt_away_over_hit": null,
    "tt_home_over_hit": null,
    "f5_tt_away_over_hit": null,
    "f5_tt_home_over_hit": null,
    "spread_away_covered": null,
    "annotated_at": null
  },
  {
    "date": "2026-07-24",
    "away": "Chicago Cubs",
    "away_code": "CHC",
    "home": "Pittsburgh Pirates",
    "home_code": "PIT",
    "game_time_utc": "2026-07-24T22:41:00Z",
    "away_pitcher": "Matthew Boyd",
    "away_pitcher_hand": "L",
    "away_pitcher_id": "571510",
    "home_pitcher": "Jared Jones",
    "home_pitcher_hand": "R",
    "home_pitcher_id": "683003",
    "ml_away": 104,
    "ml_home": -120,
    "spread_away_line": -1.5,
    "spread_away_price": 168,
    "spread_home_line": -1.5,
    "spread_home_price": 168,
    "total_line": 8.0,
    "over_price": -110,
    "under_price": -106,
    "f5_ml_away": 102,
    "f5_ml_home": -128,
    "f5_spread_away_line": 0.5,
    "f5_spread_away_price": -148,
    "f5_spread_home_line": -0.5,
    "f5_spread_home_price": 114,
    "f5_total_line": 4.5,
    "f5_over_price": 108,
    "f5_under_price": -140,
    "tt_away_line": 3.5,
    "tt_away_over_price": -130,
    "tt_away_under_price": 105,
    "tt_home_line": 3.5,
    "tt_home_over_price": -142,
    "tt_home_under_price": 114,
    "f5_tt_away_line": 1.5,
    "f5_tt_away_over_price": -130,
    "f5_tt_away_under_price": 100,
    "f5_tt_home_line": 1.5,
    "f5_tt_home_over_price": -160,
    "f5_tt_home_under_price": 124,
    "pitchers": [
      {
        "name": "Jared Jones",
        "k_line": 5.5,
        "k_over_price": 110,
        "k_under_price": -128,
        "outs_line": 14.5,
        "outs_over_price": -155,
        "outs_under_price": 120,
        "actual_ks": null,
        "actual_outs": null,
        "k_over_hit": null,
        "outs_over_hit": null
      },
      {
        "name": "Matthew Boyd",
        "k_line": 5.5,
        "k_over_price": 106,
        "k_under_price": -134,
        "outs_line": 16.5,
        "outs_over_price": -104,
        "outs_under_price": -128,
        "actual_ks": null,
        "actual_outs": null,
        "k_over_hit": null,
        "outs_over_hit": null
      }
    ],
    "odds_recorded_at": "2026-07-24T09:42:57.916907+00:00",
    "odds_final": false,
    "away_score": null,
    "home_score": null,
    "total_runs": null,
    "home_win": null,
    "over_hit": null,
    "away_f5_score": null,
    "home_f5_score": null,
    "f5_total_runs": null,
    "f5_home_win": null,
    "f5_over_hit": null,
    "f5_spread_away_covered": null,
    "tt_away_over_hit": null,
    "tt_home_over_hit": null,
    "f5_tt_away_over_hit": null,
    "f5_tt_home_over_hit": null,
    "spread_away_covered": null,
    "annotated_at": null
  },
  {
    "date": "2026-07-24",
    "away": "Kansas City Royals",
    "away_code": "KCR",
    "home": "Detroit Tigers",
    "home_code": "DET",
    "game_time_utc": "2026-07-24T22:41:00Z",
    "away_pitcher": "Noah Cameron",
    "away_pitcher_hand": "L",
    "away_pitcher_id": "702070",
    "home_pitcher": "Tarik Skubal",
    "home_pitcher_hand": "L",
    "home_pitcher_id": "669373",
    "ml_away": 241,
    "ml_home": -285,
    "spread_away_line": 1.5,
    "spread_away_price": 110,
    "spread_home_line": -1.5,
    "spread_home_price": -128,
    "total_line": 7.5,
    "over_price": -105,
    "under_price": -105,
    "f5_ml_away": 255,
    "f5_ml_home": -340,
    "f5_spread_away_line": 1.5,
    "f5_spread_away_price": -128,
    "f5_spread_home_line": -1.5,
    "f5_spread_home_price": -102,
    "f5_total_line": 3.5,
    "f5_over_price": -140,
    "f5_under_price": 108,
    "tt_away_line": 2.5,
    "tt_away_over_price": -115,
    "tt_away_under_price": -111,
    "tt_home_line": 4.5,
    "tt_home_over_price": -115,
    "tt_home_under_price": -105,
    "f5_tt_away_line": null,
    "f5_tt_away_over_price": null,
    "f5_tt_away_under_price": null,
    "f5_tt_home_line": null,
    "f5_tt_home_over_price": null,
    "f5_tt_home_under_price": null,
    "pitchers": [
      {
        "name": "Tarik Skubal",
        "k_line": 8.5,
        "k_over_price": 114,
        "k_under_price": 120,
        "outs_line": 18.5,
        "outs_over_price": -102,
        "outs_under_price": -130,
        "actual_ks": null,
        "actual_outs": null,
        "k_over_hit": null,
        "outs_over_hit": null
      }
    ],
    "odds_recorded_at": "2026-07-24T09:42:57.916907+00:00",
    "odds_final": false,
    "away_score": null,
    "home_score": null,
    "total_runs": null,
    "home_win": null,
    "over_hit": null,
    "away_f5_score": null,
    "home_f5_score": null,
    "f5_total_runs": null,
    "f5_home_win": null,
    "f5_over_hit": null,
    "f5_spread_away_covered": null,
    "tt_away_over_hit": null,
    "tt_home_over_hit": null,
    "f5_tt_away_over_hit": null,
    "f5_tt_home_over_hit": null,
    "spread_away_covered": null,
    "annotated_at": null
  },
  {
    "date": "2026-07-24",
    "away": "Arizona Diamondbacks",
    "away_code": "ARI",
    "home": "Washington Nationals",
    "home_code": "WSN",
    "game_time_utc": "2026-07-24T22:46:00Z",
    "away_pitcher": "E. Rodriguez",
    "away_pitcher_hand": "L",
    "away_pitcher_id": "593958",
    "home_pitcher": "Zack Littell",
    "home_pitcher_hand": "R",
    "home_pitcher_id": "641793",
    "ml_away": -120,
    "ml_home": 105,
    "spread_away_line": -1.5,
    "spread_away_price": 135,
    "spread_home_line": 1.5,
    "spread_home_price": -156,
    "total_line": 9.5,
    "over_price": -108,
    "under_price": -110,
    "f5_ml_away": -120,
    "f5_ml_home": -104,
    "f5_spread_away_line": -0.5,
    "f5_spread_away_price": 112,
    "f5_spread_home_line": 0.5,
    "f5_spread_home_price": -146,
    "f5_total_line": 5.5,
    "f5_over_price": -102,
    "f5_under_price": -128,
    "tt_away_line": 4.5,
    "tt_away_over_price": -130,
    "tt_away_under_price": 105,
    "tt_home_line": 4.5,
    "tt_home_over_price": -102,
    "tt_home_under_price": -125,
    "f5_tt_away_line": 2.5,
    "f5_tt_away_over_price": -105,
    "f5_tt_away_under_price": -125,
    "f5_tt_home_line": 2.5,
    "f5_tt_home_over_price": 105,
    "f5_tt_home_under_price": -135,
    "pitchers": [
      {
        "name": "Eduardo Rodriguez",
        "k_line": 4.5,
        "k_over_price": 120,
        "k_under_price": -147,
        "outs_line": 17.5,
        "outs_over_price": -120,
        "outs_under_price": -105,
        "actual_ks": null,
        "actual_outs": null,
        "k_over_hit": null,
        "outs_over_hit": null
      }
    ],
    "odds_recorded_at": "2026-07-24T09:42:57.916907+00:00",
    "odds_final": false,
    "away_score": null,
    "home_score": null,
    "total_runs": null,
    "home_win": null,
    "over_hit": null,
    "away_f5_score": null,
    "home_f5_score": null,
    "f5_total_runs": null,
    "f5_home_win": null,
    "f5_over_hit": null,
    "f5_spread_away_covered": null,
    "tt_away_over_hit": null,
    "tt_home_over_hit": null,
    "f5_tt_away_over_hit": null,
    "f5_tt_home_over_hit": null,
    "spread_away_covered": null,
    "annotated_at": null
  },
  {
    "date": "2026-07-24",
    "away": "New York Yankees",
    "away_code": "NYY",
    "home": "Philadelphia Phillies",
    "home_code": "PHI",
    "game_time_utc": "2026-07-24T22:46:00Z",
    "away_pitcher": "Cam Schlittler",
    "away_pitcher_hand": "R",
    "away_pitcher_id": "693645",
    "home_pitcher": "Jesus Luzardo",
    "home_pitcher_hand": "L",
    "home_pitcher_id": "666200",
    "ml_away": 115,
    "ml_home": -122,
    "spread_away_line": -1.5,
    "spread_away_price": 162,
    "spread_home_line": -1.5,
    "spread_home_price": 160,
    "total_line": 8.0,
    "over_price": 100,
    "under_price": 100,
    "f5_ml_away": 105,
    "f5_ml_home": -120,
    "f5_spread_away_line": 0.5,
    "f5_spread_away_price": -154,
    "f5_spread_home_line": -0.5,
    "f5_spread_home_price": 118,
    "f5_total_line": 3.5,
    "f5_over_price": -152,
    "f5_under_price": 116,
    "tt_away_line": 3.5,
    "tt_away_over_price": -122,
    "tt_away_under_price": -104,
    "tt_home_line": 3.5,
    "tt_home_over_price": -128,
    "tt_home_under_price": 114,
    "f5_tt_away_line": 1.5,
    "f5_tt_away_over_price": -135,
    "f5_tt_away_under_price": 105,
    "f5_tt_home_line": 1.5,
    "f5_tt_home_over_price": -154,
    "f5_tt_home_under_price": 120,
    "pitchers": [
      {
        "name": "Cam Schlittler",
        "k_line": 7.5,
        "k_over_price": 112,
        "k_under_price": 126,
        "outs_line": 17.5,
        "outs_over_price": -163,
        "outs_under_price": 122,
        "actual_ks": null,
        "actual_outs": null,
        "k_over_hit": null,
        "outs_over_hit": null
      },
      {
        "name": "Jesus Luzardo",
        "k_line": 7.5,
        "k_over_price": 108,
        "k_under_price": -112,
        "outs_line": 17.5,
        "outs_over_price": -150,
        "outs_under_price": 130,
        "actual_ks": null,
        "actual_outs": null,
        "k_over_hit": null,
        "outs_over_hit": null
      }
    ],
    "odds_recorded_at": "2026-07-24T09:42:57.916907+00:00",
    "odds_final": false,
    "away_score": null,
    "home_score": null,
    "total_runs": null,
    "home_win": null,
    "over_hit": null,
    "away_f5_score": null,
    "home_f5_score": null,
    "f5_total_runs": null,
    "f5_home_win": null,
    "f5_over_hit": null,
    "f5_spread_away_covered": null,
    "tt_away_over_hit": null,
    "tt_home_over_hit": null,
    "f5_tt_away_over_hit": null,
    "f5_tt_home_over_hit": null,
    "spread_away_covered": null,
    "annotated_at": null
  },
  {
    "date": "2026-07-24",
    "away": "Atlanta Braves",
    "away_code": "ATL",
    "home": "Baltimore Orioles",
    "home_code": "BAL",
    "game_time_utc": "2026-07-24T23:06:00Z",
    "away_pitcher": "Grant Holmes",
    "away_pitcher_hand": "R",
    "away_pitcher_id": "656550",
    "home_pitcher": "Trevor Rogers",
    "home_pitcher_hand": "L",
    "home_pitcher_id": "669432",
    "ml_away": -101,
    "ml_home": -115,
    "spread_away_line": -1.5,
    "spread_away_price": 160,
    "spread_home_line": 1.5,
    "spread_home_price": -184,
    "total_line": 9.0,
    "over_price": -108,
    "under_price": -110,
    "f5_ml_away": 102,
    "f5_ml_home": -124,
    "f5_spread_away_line": 0.5,
    "f5_spread_away_price": -138,
    "f5_spread_home_line": -0.5,
    "f5_spread_home_price": 106,
    "f5_total_line": 4.5,
    "f5_over_price": -140,
    "f5_under_price": 108,
    "tt_away_line": 4.5,
    "tt_away_over_price": 100,
    "tt_away_under_price": -125,
    "tt_home_line": 4.5,
    "tt_home_over_price": 102,
    "tt_home_under_price": -125,
    "f5_tt_away_line": 2.5,
    "f5_tt_away_over_price": 114,
    "f5_tt_away_under_price": -145,
    "f5_tt_home_line": 2.5,
    "f5_tt_home_over_price": -105,
    "f5_tt_home_under_price": -125,
    "pitchers": [
      {
        "name": "Grant Holmes",
        "k_line": 4.5,
        "k_over_price": -150,
        "k_under_price": 120,
        "outs_line": 14.5,
        "outs_over_price": -173,
        "outs_under_price": 130,
        "actual_ks": null,
        "actual_outs": null,
        "k_over_hit": null,
        "outs_over_hit": null
      },
      {
        "name": "Trevor Rogers",
        "k_line": 5.5,
        "k_over_price": 123,
        "k_under_price": 116,
        "outs_line": 17.5,
        "outs_over_price": -155,
        "outs_under_price": 133,
        "actual_ks": null,
        "actual_outs": null,
        "k_over_hit": null,
        "outs_over_hit": null
      }
    ],
    "odds_recorded_at": "2026-07-24T09:42:57.916907+00:00",
    "odds_final": false,
    "away_score": null,
    "home_score": null,
    "total_runs": null,
    "home_win": null,
    "over_hit": null,
    "away_f5_score": null,
    "home_f5_score": null,
    "f5_total_runs": null,
    "f5_home_win": null,
    "f5_over_hit": null,
    "f5_spread_away_covered": null,
    "tt_away_over_hit": null,
    "tt_home_over_hit": null,
    "f5_tt_away_over_hit": null,
    "f5_tt_home_over_hit": null,
    "spread_away_covered": null,
    "annotated_at": null
  },
  {
    "date": "2026-07-24",
    "away": "Cleveland Guardians",
    "away_code": "CLE",
    "home": "Tampa Bay Rays",
    "home_code": "TBR",
    "game_time_utc": "2026-07-24T23:11:00Z",
    "away_pitcher": "Joey Cantillo",
    "away_pitcher_hand": "L",
    "away_pitcher_id": "676282",
    "home_pitcher": "Shane McClanahan",
    "home_pitcher_hand": "L",
    "home_pitcher_id": "663556",
    "ml_away": 118,
    "ml_home": -137,
    "spread_away_line": 1.5,
    "spread_away_price": -186,
    "spread_home_line": -1.5,
    "spread_home_price": 164,
    "total_line": 7.5,
    "over_price": -105,
    "under_price": -113,
    "f5_ml_away": 114,
    "f5_ml_home": -142,
    "f5_spread_away_line": 0.5,
    "f5_spread_away_price": -135,
    "f5_spread_home_line": -0.5,
    "f5_spread_home_price": 104,
    "f5_total_line": 3.5,
    "f5_over_price": -146,
    "f5_under_price": 112,
    "tt_away_line": 3.5,
    "tt_away_over_price": -102,
    "tt_away_under_price": -125,
    "tt_home_line": 3.5,
    "tt_home_over_price": -125,
    "tt_home_under_price": 105,
    "f5_tt_away_line": 1.5,
    "f5_tt_away_over_price": -125,
    "f5_tt_away_under_price": -105,
    "f5_tt_home_line": 2.5,
    "f5_tt_home_over_price": 124,
    "f5_tt_home_under_price": -160,
    "pitchers": [
      {
        "name": "Joey Cantillo",
        "k_line": 4.5,
        "k_over_price": -146,
        "k_under_price": 121,
        "outs_line": 15.5,
        "outs_over_price": 113,
        "outs_under_price": -150,
        "actual_ks": null,
        "actual_outs": null,
        "k_over_hit": null,
        "outs_over_hit": null
      },
      {
        "name": "Shane McClanahan",
        "k_line": 5.5,
        "k_over_price": 105,
        "k_under_price": -122,
        "outs_line": 15.5,
        "outs_over_price": -129,
        "outs_under_price": -103,
        "actual_ks": null,
        "actual_outs": null,
        "k_over_hit": null,
        "outs_over_hit": null
      }
    ],
    "odds_recorded_at": "2026-07-24T09:42:57.916907+00:00",
    "odds_final": false,
    "away_score": null,
    "home_score": null,
    "total_runs": null,
    "home_win": null,
    "over_hit": null,
    "away_f5_score": null,
    "home_f5_score": null,
    "f5_total_runs": null,
    "f5_home_win": null,
    "f5_over_hit": null,
    "f5_spread_away_covered": null,
    "tt_away_over_hit": null,
    "tt_home_over_hit": null,
    "f5_tt_away_over_hit": null,
    "f5_tt_home_over_hit": null,
    "spread_away_covered": null,
    "annotated_at": null
  },
  {
    "date": "2026-07-24",
    "away": "Los Angeles Dodgers",
    "away_code": "LAD",
    "home": "New York Mets",
    "home_code": "NYM",
    "game_time_utc": "2026-07-24T23:11:00Z",
    "away_pitcher": "Roki Sasaki",
    "away_pitcher_hand": "R",
    "away_pitcher_id": "808963",
    "home_pitcher": "Sean Manaea",
    "home_pitcher_hand": "L",
    "home_pitcher_id": "640455",
    "ml_away": -148,
    "ml_home": 129,
    "spread_away_line": -1.5,
    "spread_away_price": 114,
    "spread_home_line": 1.5,
    "spread_home_price": -125,
    "total_line": 9.0,
    "over_price": -105,
    "under_price": -114,
    "f5_ml_away": -145,
    "f5_ml_home": 120,
    "f5_spread_away_line": -0.5,
    "f5_spread_away_price": -106,
    "f5_spread_home_line": 0.5,
    "f5_spread_home_price": -122,
    "f5_total_line": 4.5,
    "f5_over_price": -144,
    "f5_under_price": 110,
    "tt_away_line": 4.5,
    "tt_away_over_price": -125,
    "tt_away_under_price": 100,
    "tt_home_line": 3.5,
    "tt_home_over_price": -128,
    "tt_home_under_price": 100,
    "f5_tt_away_line": 2.5,
    "f5_tt_away_over_price": -115,
    "f5_tt_away_under_price": -115,
    "f5_tt_home_line": 1.5,
    "f5_tt_home_over_price": -166,
    "f5_tt_home_under_price": 130,
    "pitchers": [
      {
        "name": "Roki Sasaki",
        "k_line": 5.5,
        "k_over_price": 128,
        "k_under_price": -164,
        "outs_line": 16.5,
        "outs_over_price": -112,
        "outs_under_price": -115,
        "actual_ks": null,
        "actual_outs": null,
        "k_over_hit": null,
        "outs_over_hit": null
      },
      {
        "name": "Sean Manaea",
        "k_line": 5.5,
        "k_over_price": 120,
        "k_under_price": 128,
        "outs_line": 15.5,
        "outs_over_price": -134,
        "outs_under_price": 101,
        "actual_ks": null,
        "actual_outs": null,
        "k_over_hit": null,
        "outs_over_hit": null
      }
    ],
    "odds_recorded_at": "2026-07-24T09:42:57.916907+00:00",
    "odds_final": false,
    "away_score": null,
    "home_score": null,
    "total_runs": null,
    "home_win": null,
    "over_hit": null,
    "away_f5_score": null,
    "home_f5_score": null,
    "f5_total_runs": null,
    "f5_home_win": null,
    "f5_over_hit": null,
    "f5_spread_away_covered": null,
    "tt_away_over_hit": null,
    "tt_home_over_hit": null,
    "f5_tt_away_over_hit": null,
    "f5_tt_home_over_hit": null,
    "spread_away_covered": null,
    "annotated_at": null
  },
  {
    "date": "2026-07-24",
    "away": "San Diego Padres",
    "away_code": "SDP",
    "home": "Miami Marlins",
    "home_code": "MIA",
    "game_time_utc": "2026-07-24T23:11:00Z",
    "away_pitcher": "German Marquez",
    "away_pitcher_hand": "R",
    "away_pitcher_id": "608566",
    "home_pitcher": "Ryan Gusto",
    "home_pitcher_hand": "R",
    "home_pitcher_id": "687473",
    "ml_away": 116,
    "ml_home": -136,
    "spread_away_line": 1.5,
    "spread_away_price": -175,
    "spread_home_line": -1.5,
    "spread_home_price": 158,
    "total_line": 9.0,
    "over_price": -102,
    "under_price": -115,
    "f5_ml_away": 120,
    "f5_ml_home": -150,
    "f5_spread_away_line": 0.5,
    "f5_spread_away_price": -118,
    "f5_spread_home_line": -0.5,
    "f5_spread_home_price": -110,
    "f5_total_line": 4.5,
    "f5_over_price": -146,
    "f5_under_price": 112,
    "tt_away_line": 4.5,
    "tt_away_over_price": 114,
    "tt_away_under_price": -142,
    "tt_home_line": 4.5,
    "tt_home_over_price": -104,
    "tt_home_under_price": -120,
    "f5_tt_away_line": null,
    "f5_tt_away_over_price": null,
    "f5_tt_away_under_price": null,
    "f5_tt_home_line": null,
    "f5_tt_home_over_price": null,
    "f5_tt_home_under_price": null,
    "pitchers": [
      {
        "name": "German Marquez",
        "k_line": 3.5,
        "k_over_price": 114,
        "k_under_price": -136,
        "outs_line": 14.5,
        "outs_over_price": -160,
        "outs_under_price": 121,
        "actual_ks": null,
        "actual_outs": null,
        "k_over_hit": null,
        "outs_over_hit": null
      }
    ],
    "odds_recorded_at": "2026-07-24T09:42:57.916907+00:00",
    "odds_final": false,
    "away_score": null,
    "home_score": null,
    "total_runs": null,
    "home_win": null,
    "over_hit": null,
    "away_f5_score": null,
    "home_f5_score": null,
    "f5_total_runs": null,
    "f5_home_win": null,
    "f5_over_hit": null,
    "f5_spread_away_covered": null,
    "tt_away_over_hit": null,
    "tt_home_over_hit": null,
    "f5_tt_away_over_hit": null,
    "f5_tt_home_over_hit": null,
    "spread_away_covered": null,
    "annotated_at": null
  },
  {
    "date": "2026-07-24",
    "away": "Toronto Blue Jays",
    "away_code": "TOR",
    "home": "Boston Red Sox",
    "home_code": "BOS",
    "game_time_utc": "2026-07-24T23:16:00Z",
    "away_pitcher": "Trey Yesavage",
    "away_pitcher_hand": "R",
    "away_pitcher_id": "702056",
    "home_pitcher": "Patrick Sandoval",
    "home_pitcher_hand": "L",
    "home_pitcher_id": "663776",
    "ml_away": 105,
    "ml_home": -122,
    "spread_away_line": 1.5,
    "spread_away_price": -199,
    "spread_home_line": -1.5,
    "spread_home_price": 172,
    "total_line": 8.5,
    "over_price": -110,
    "under_price": -106,
    "f5_ml_away": 102,
    "f5_ml_home": -125,
    "f5_spread_away_line": 0.5,
    "f5_spread_away_price": -140,
    "f5_spread_home_line": -0.5,
    "f5_spread_home_price": 108,
    "f5_total_line": 4.5,
    "f5_over_price": -125,
    "f5_under_price": -104,
    "tt_away_line": 3.5,
    "tt_away_over_price": -148,
    "tt_away_under_price": 120,
    "tt_home_line": 4.5,
    "tt_home_over_price": 112,
    "tt_home_under_price": -135,
    "f5_tt_away_line": 1.5,
    "f5_tt_away_over_price": -160,
    "f5_tt_away_under_price": 124,
    "f5_tt_home_line": 2.5,
    "f5_tt_home_over_price": 120,
    "f5_tt_home_under_price": -154,
    "pitchers": [
      {
        "name": "Patrick Sandoval",
        "k_line": 4.5,
        "k_over_price": 114,
        "k_under_price": -128,
        "outs_line": 15.5,
        "outs_over_price": 111,
        "outs_under_price": -140,
        "actual_ks": null,
        "actual_outs": null,
        "k_over_hit": null,
        "outs_over_hit": null
      },
      {
        "name": "Trey Yesavage",
        "k_line": 5.5,
        "k_over_price": 100,
        "k_under_price": -123,
        "outs_line": 17.5,
        "outs_over_price": -122,
        "outs_under_price": 100,
        "actual_ks": null,
        "actual_outs": null,
        "k_over_hit": null,
        "outs_over_hit": null
      }
    ],
    "odds_recorded_at": "2026-07-24T09:42:57.916907+00:00",
    "odds_final": false,
    "away_score": null,
    "home_score": null,
    "total_runs": null,
    "home_win": null,
    "over_hit": null,
    "away_f5_score": null,
    "home_f5_score": null,
    "f5_total_runs": null,
    "f5_home_win": null,
    "f5_over_hit": null,
    "f5_spread_away_covered": null,
    "tt_away_over_hit": null,
    "tt_home_over_hit": null,
    "f5_tt_away_over_hit": null,
    "f5_tt_home_over_hit": null,
    "spread_away_covered": null,
    "annotated_at": null
  },
  {
    "date": "2026-07-24",
    "away": "Houston Astros",
    "away_code": "HOU",
    "home": "Chicago White Sox",
    "home_code": "CHW",
    "game_time_utc": "2026-07-24T23:41:00Z",
    "away_pitcher": "S. Arrighetti",
    "away_pitcher_hand": "R",
    "away_pitcher_id": "681293",
    "home_pitcher": "Davis Martin",
    "home_pitcher_hand": "R",
    "home_pitcher_id": "663436",
    "ml_away": 116,
    "ml_home": -130,
    "spread_away_line": 1.5,
    "spread_away_price": -170,
    "spread_home_line": -1.5,
    "spread_home_price": 147,
    "total_line": 8.5,
    "over_price": -115,
    "under_price": 100,
    "f5_ml_away": 122,
    "f5_ml_home": -140,
    "f5_spread_away_line": 0.5,
    "f5_spread_away_price": -120,
    "f5_spread_home_line": -0.5,
    "f5_spread_home_price": -108,
    "f5_total_line": 4.5,
    "f5_over_price": -128,
    "f5_under_price": -102,
    "tt_away_line": 4.5,
    "tt_away_over_price": 114,
    "tt_away_under_price": 106,
    "tt_home_line": 4.5,
    "tt_home_over_price": 100,
    "tt_home_under_price": -125,
    "f5_tt_away_line": 1.5,
    "f5_tt_away_over_price": -160,
    "f5_tt_away_under_price": 124,
    "f5_tt_home_line": 2.5,
    "f5_tt_home_over_price": 100,
    "f5_tt_home_under_price": -130,
    "pitchers": [
      {
        "name": "Davis Martin",
        "k_line": 4.5,
        "k_over_price": 120,
        "k_under_price": -132,
        "outs_line": 15.5,
        "outs_over_price": 102,
        "outs_under_price": -129,
        "actual_ks": null,
        "actual_outs": null,
        "k_over_hit": null,
        "outs_over_hit": null
      },
      {
        "name": "Spencer Arrighetti",
        "k_line": 5.5,
        "k_over_price": 113,
        "k_under_price": -136,
        "outs_line": 15.5,
        "outs_over_price": 111,
        "outs_under_price": -147,
        "actual_ks": null,
        "actual_outs": null,
        "k_over_hit": null,
        "outs_over_hit": null
      }
    ],
    "odds_recorded_at": "2026-07-24T09:42:57.916907+00:00",
    "odds_final": false,
    "away_score": null,
    "home_score": null,
    "total_runs": null,
    "home_win": null,
    "over_hit": null,
    "away_f5_score": null,
    "home_f5_score": null,
    "f5_total_runs": null,
    "f5_home_win": null,
    "f5_over_hit": null,
    "f5_spread_away_covered": null,
    "tt_away_over_hit": null,
    "tt_home_over_hit": null,
    "f5_tt_away_over_hit": null,
    "f5_tt_home_over_hit": null,
    "spread_away_covered": null,
    "annotated_at": null
  },
  {
    "date": "2026-07-24",
    "away": "Seattle Mariners",
    "away_code": "SEA",
    "home": "Texas Rangers",
    "home_code": "TEX",
    "game_time_utc": "2026-07-25T00:06:00Z",
    "away_pitcher": "Bryce Miller",
    "away_pitcher_hand": "R",
    "away_pitcher_id": "682243",
    "home_pitcher": "MacKenzie Gore",
    "home_pitcher_hand": "L",
    "home_pitcher_id": "669022",
    "ml_away": -118,
    "ml_home": 101,
    "spread_away_line": -1.5,
    "spread_away_price": 146,
    "spread_home_line": 1.5,
    "spread_home_price": -168,
    "total_line": 7.5,
    "over_price": -110,
    "under_price": -108,
    "f5_ml_away": -118,
    "f5_ml_home": -105,
    "f5_spread_away_line": -0.5,
    "f5_spread_away_price": 122,
    "f5_spread_home_line": 0.5,
    "f5_spread_home_price": -160,
    "f5_total_line": 3.5,
    "f5_over_price": -144,
    "f5_under_price": 110,
    "tt_away_line": 3.5,
    "tt_away_over_price": -130,
    "tt_away_under_price": 105,
    "tt_home_line": 3.5,
    "tt_home_over_price": -104,
    "tt_home_under_price": -120,
    "f5_tt_away_line": 1.5,
    "f5_tt_away_over_price": -140,
    "f5_tt_away_under_price": 110,
    "f5_tt_home_line": 1.5,
    "f5_tt_home_over_price": -130,
    "f5_tt_home_under_price": 100,
    "pitchers": [
      {
        "name": "Bryce Miller",
        "k_line": 5.5,
        "k_over_price": -148,
        "k_under_price": 119,
        "outs_line": 17.5,
        "outs_over_price": -155,
        "outs_under_price": 130,
        "actual_ks": null,
        "actual_outs": null,
        "k_over_hit": null,
        "outs_over_hit": null
      },
      {
        "name": "MacKenzie Gore",
        "k_line": 5.5,
        "k_over_price": -151,
        "k_under_price": 134,
        "outs_line": 17.5,
        "outs_over_price": -128,
        "outs_under_price": -102,
        "actual_ks": null,
        "actual_outs": null,
        "k_over_hit": null,
        "outs_over_hit": null
      }
    ],
    "odds_recorded_at": "2026-07-24T09:42:57.916907+00:00",
    "odds_final": false,
    "away_score": null,
    "home_score": null,
    "total_runs": null,
    "home_win": null,
    "over_hit": null,
    "away_f5_score": null,
    "home_f5_score": null,
    "f5_total_runs": null,
    "f5_home_win": null,
    "f5_over_hit": null,
    "f5_spread_away_covered": null,
    "tt_away_over_hit": null,
    "tt_home_over_hit": null,
    "f5_tt_away_over_hit": null,
    "f5_tt_home_over_hit": null,
    "spread_away_covered": null,
    "annotated_at": null
  },
  {
    "date": "2026-07-24",
    "away": "Athletics",
    "away_code": "ATH",
    "home": "Minnesota Twins",
    "home_code": "MIN",
    "game_time_utc": "2026-07-25T00:11:00Z",
    "away_pitcher": "Jacob Lopez",
    "away_pitcher_hand": "L",
    "away_pitcher_id": "682052",
    "home_pitcher": "Zebby Matthews",
    "home_pitcher_hand": "R",
    "home_pitcher_id": "805673",
    "ml_away": 126,
    "ml_home": -140,
    "spread_away_line": 1.5,
    "spread_away_price": -170,
    "spread_home_line": -1.5,
    "spread_home_price": 142,
    "total_line": 9.5,
    "over_price": -110,
    "under_price": -102,
    "f5_ml_away": 116,
    "f5_ml_home": -145,
    "f5_spread_away_line": 0.5,
    "f5_spread_away_price": -120,
    "f5_spread_home_line": -0.5,
    "f5_spread_home_price": -108,
    "f5_total_line": 5.5,
    "f5_over_price": 104,
    "f5_under_price": -135,
    "tt_away_line": 4.5,
    "tt_away_over_price": -104,
    "tt_away_under_price": -122,
    "tt_home_line": 4.5,
    "tt_home_over_price": -135,
    "tt_home_under_price": 112,
    "f5_tt_away_line": 2.5,
    "f5_tt_away_over_price": 120,
    "f5_tt_away_under_price": -154,
    "f5_tt_home_line": 2.5,
    "f5_tt_home_over_price": -125,
    "f5_tt_home_under_price": -105,
    "pitchers": [
      {
        "name": "Jacob Lopez",
        "k_line": 4.5,
        "k_over_price": 120,
        "k_under_price": -138,
        "outs_line": null,
        "outs_over_price": null,
        "outs_under_price": null,
        "actual_ks": null,
        "actual_outs": null,
        "k_over_hit": null,
        "outs_over_hit": null
      },
      {
        "name": "Zebby Matthews",
        "k_line": 4.5,
        "k_over_price": 120,
        "k_under_price": -146,
        "outs_line": 17.5,
        "outs_over_price": -166,
        "outs_under_price": 145,
        "actual_ks": null,
        "actual_outs": null,
        "k_over_hit": null,
        "outs_over_hit": null
      }
    ],
    "odds_recorded_at": "2026-07-24T09:42:57.916907+00:00",
    "odds_final": false,
    "away_score": null,
    "home_score": null,
    "total_runs": null,
    "home_win": null,
    "over_hit": null,
    "away_f5_score": null,
    "home_f5_score": null,
    "f5_total_runs": null,
    "f5_home_win": null,
    "f5_over_hit": null,
    "f5_spread_away_covered": null,
    "tt_away_over_hit": null,
    "tt_home_over_hit": null,
    "f5_tt_away_over_hit": null,
    "f5_tt_home_over_hit": null,
    "spread_away_covered": null,
    "annotated_at": null
  },
  {
    "date": "2026-07-24",
    "away": "Cincinnati Reds",
    "away_code": "CIN",
    "home": "St. Louis Cardinals",
    "home_code": "STL",
    "game_time_utc": "2026-07-25T00:16:00Z",
    "away_pitcher": "Rhett Lowder",
    "away_pitcher_hand": "R",
    "away_pitcher_id": "695076",
    "home_pitcher": "Dustin May",
    "home_pitcher_hand": "R",
    "home_pitcher_id": "669160",
    "ml_away": 139,
    "ml_home": -164,
    "spread_away_line": 1.5,
    "spread_away_price": -154,
    "spread_home_line": -1.5,
    "spread_home_price": 130,
    "total_line": 8.5,
    "over_price": -102,
    "under_price": -110,
    "f5_ml_away": 136,
    "f5_ml_home": -160,
    "f5_spread_away_line": 0.5,
    "f5_spread_away_price": -110,
    "f5_spread_home_line": -0.5,
    "f5_spread_home_price": -118,
    "f5_total_line": 4.5,
    "f5_over_price": -120,
    "f5_under_price": -108,
    "tt_away_line": 3.5,
    "tt_away_over_price": -115,
    "tt_away_under_price": -111,
    "tt_home_line": 4.5,
    "tt_home_over_price": -105,
    "tt_home_under_price": -115,
    "f5_tt_away_line": 1.5,
    "f5_tt_away_over_price": -135,
    "f5_tt_away_under_price": 105,
    "f5_tt_home_line": 2.5,
    "f5_tt_home_over_price": 105,
    "f5_tt_home_under_price": -135,
    "pitchers": [
      {
        "name": "Dustin May",
        "k_line": 5.5,
        "k_over_price": -102,
        "k_under_price": -108,
        "outs_line": 17.5,
        "outs_over_price": -160,
        "outs_under_price": 130,
        "actual_ks": null,
        "actual_outs": null,
        "k_over_hit": null,
        "outs_over_hit": null
      },
      {
        "name": "Rhett Lowder",
        "k_line": 3.5,
        "k_over_price": 117,
        "k_under_price": -142,
        "outs_line": null,
        "outs_over_price": null,
        "outs_under_price": null,
        "actual_ks": null,
        "actual_outs": null,
        "k_over_hit": null,
        "outs_over_hit": null
      }
    ],
    "odds_recorded_at": "2026-07-24T09:42:57.916907+00:00",
    "odds_final": false,
    "away_score": null,
    "home_score": null,
    "total_runs": null,
    "home_win": null,
    "over_hit": null,
    "away_f5_score": null,
    "home_f5_score": null,
    "f5_total_runs": null,
    "f5_home_win": null,
    "f5_over_hit": null,
    "f5_spread_away_covered": null,
    "tt_away_over_hit": null,
    "tt_home_over_hit": null,
    "f5_tt_away_over_hit": null,
    "f5_tt_home_over_hit": null,
    "spread_away_covered": null,
    "annotated_at": null
  },
  {
    "date": "2026-07-24",
    "away": "Los Angeles Angels",
    "away_code": "LAA",
    "home": "San Francisco Giants",
    "home_code": "SFG",
    "game_time_utc": "2026-07-25T02:16:00Z",
    "away_pitcher": "G. Rodriguez",
    "away_pitcher_hand": "R",
    "away_pitcher_id": "680570",
    "home_pitcher": "Logan Webb",
    "home_pitcher_hand": "R",
    "home_pitcher_id": "657277",
    "ml_away": 146,
    "ml_home": -170,
    "spread_away_line": 1.5,
    "spread_away_price": -150,
    "spread_home_line": -1.5,
    "spread_home_price": 130,
    "total_line": 8.0,
    "over_price": -105,
    "under_price": -113,
    "f5_ml_away": 158,
    "f5_ml_home": -188,
    "f5_spread_away_line": 0.5,
    "f5_spread_away_price": 104,
    "f5_spread_home_line": -0.5,
    "f5_spread_home_price": -135,
    "f5_total_line": 4.5,
    "f5_over_price": 106,
    "f5_under_price": -138,
    "tt_away_line": 3.5,
    "tt_away_over_price": 100,
    "tt_away_under_price": -125,
    "tt_home_line": 4.5,
    "tt_home_over_price": 102,
    "tt_home_under_price": -130,
    "f5_tt_away_line": 1.5,
    "f5_tt_away_over_price": -110,
    "f5_tt_away_under_price": -120,
    "f5_tt_home_line": 2.5,
    "f5_tt_home_over_price": 105,
    "f5_tt_home_under_price": -135,
    "pitchers": [
      {
        "name": "Grayson Rodriguez",
        "k_line": 4.5,
        "k_over_price": 130,
        "k_under_price": -141,
        "outs_line": 15.5,
        "outs_over_price": -108,
        "outs_under_price": -108,
        "actual_ks": null,
        "actual_outs": null,
        "k_over_hit": null,
        "outs_over_hit": null
      },
      {
        "name": "Logan Webb",
        "k_line": 5.5,
        "k_over_price": -156,
        "k_under_price": 128,
        "outs_line": 18.5,
        "outs_over_price": -114,
        "outs_under_price": -102,
        "actual_ks": null,
        "actual_outs": null,
        "k_over_hit": null,
        "outs_over_hit": null
      }
    ],
    "odds_recorded_at": "2026-07-24T09:42:57.916907+00:00",
    "odds_final": false,
    "away_score": null,
    "home_score": null,
    "total_runs": null,
    "home_win": null,
    "over_hit": null,
    "away_f5_score": null,
    "home_f5_score": null,
    "f5_total_runs": null,
    "f5_home_win": null,
    "f5_over_hit": null,
    "f5_spread_away_covered": null,
    "tt_away_over_hit": null,
    "tt_home_over_hit": null,
    "f5_tt_away_over_hit": null,
    "f5_tt_home_over_hit": null,
    "spread_away_covered": null,
    "annotated_at": null
  }
]