[
  {
    "date": "2026-07-01",
    "away": "Chicago White Sox",
    "away_code": "CHW",
    "home": "Baltimore Orioles",
    "home_code": "BAL",
    "game_time_utc": "2026-07-01T16:36:00Z",
    "away_pitcher": "Noah Schultz",
    "away_pitcher_hand": "L",
    "away_pitcher_id": "702273",
    "home_pitcher": "Dean Kremer",
    "home_pitcher_hand": "R",
    "home_pitcher_id": "665152",
    "ml_away": 120,
    "ml_home": -140,
    "spread_away_line": 1.5,
    "spread_away_price": -170,
    "spread_home_line": -1.5,
    "spread_home_price": 145,
    "total_line": 10.0,
    "over_price": -105,
    "under_price": -110,
    "f5_ml_away": 114,
    "f5_ml_home": -142,
    "f5_spread_away_line": 0.5,
    "f5_spread_away_price": -120,
    "f5_spread_home_line": -0.5,
    "f5_spread_home_price": -108,
    "f5_total_line": 5.5,
    "f5_over_price": -114,
    "f5_under_price": -114,
    "tt_away_line": 4.5,
    "tt_away_over_price": -115,
    "tt_away_under_price": -110,
    "tt_home_line": 5.5,
    "tt_home_over_price": 114,
    "tt_home_under_price": -142,
    "f5_tt_away_line": null,
    "f5_tt_away_over_price": null,
    "f5_tt_away_under_price": null,
    "f5_tt_home_line": null,
    "f5_tt_home_over_price": null,
    "f5_tt_home_under_price": null,
    "pitchers": [
      {
        "name": "Dean Kremer",
        "k_line": 5.5,
        "k_over_price": 107,
        "k_under_price": -130,
        "outs_line": 15.5,
        "outs_over_price": -110,
        "outs_under_price": -121,
        "actual_ks": 4,
        "actual_outs": 18,
        "k_over_hit": false,
        "outs_over_hit": true
      },
      {
        "name": "Noah Schultz",
        "k_line": 3.5,
        "k_over_price": -130,
        "k_under_price": 102,
        "outs_line": 13.5,
        "outs_over_price": -120,
        "outs_under_price": -111,
        "actual_ks": 7,
        "actual_outs": 13,
        "k_over_hit": true,
        "outs_over_hit": false
      }
    ],
    "odds_recorded_at": "2026-07-01T20:35:37.289760+00:00",
    "odds_final": true,
    "away_score": 1,
    "home_score": 6,
    "total_runs": 7,
    "home_win": true,
    "over_hit": false,
    "away_f5_score": 1,
    "home_f5_score": 4,
    "f5_total_runs": 5,
    "f5_home_win": true,
    "f5_over_hit": false,
    "f5_spread_away_covered": false,
    "tt_away_over_hit": false,
    "tt_home_over_hit": true,
    "f5_tt_away_over_hit": null,
    "f5_tt_home_over_hit": null,
    "spread_away_covered": false,
    "annotated_at": "2026-07-01T20:37:29.238757+00:00"
  },
  {
    "date": "2026-07-01",
    "away": "Texas Rangers",
    "away_code": "TEX",
    "home": "Cleveland Guardians",
    "home_code": "CLE",
    "game_time_utc": "2026-07-01T17:11:00Z",
    "away_pitcher": "MacKenzie Gore",
    "away_pitcher_hand": "L",
    "away_pitcher_id": "669022",
    "home_pitcher": "Joey Cantillo",
    "home_pitcher_hand": "L",
    "home_pitcher_id": "676282",
    "ml_away": -106,
    "ml_home": -110,
    "spread_away_line": -1.5,
    "spread_away_price": 160,
    "spread_home_line": 1.5,
    "spread_home_price": -187,
    "total_line": 8.5,
    "over_price": 102,
    "under_price": -103,
    "f5_ml_away": -116,
    "f5_ml_home": -108,
    "f5_spread_away_line": -0.5,
    "f5_spread_away_price": 120,
    "f5_spread_home_line": 0.5,
    "f5_spread_home_price": -156,
    "f5_total_line": 4.5,
    "f5_over_price": -110,
    "f5_under_price": -118,
    "tt_away_line": 3.5,
    "tt_away_over_price": -136,
    "tt_away_under_price": 110,
    "tt_home_line": 3.5,
    "tt_home_over_price": -132,
    "tt_home_under_price": 105,
    "f5_tt_away_line": 2.5,
    "f5_tt_away_over_price": 124,
    "f5_tt_away_under_price": -160,
    "f5_tt_home_line": 1.5,
    "f5_tt_home_over_price": -154,
    "f5_tt_home_under_price": 120,
    "pitchers": [
      {
        "name": "Joey Cantillo",
        "k_line": 5.5,
        "k_over_price": -105,
        "k_under_price": -114,
        "outs_line": 15.5,
        "outs_over_price": -118,
        "outs_under_price": -112,
        "actual_ks": 4,
        "actual_outs": 15,
        "k_over_hit": false,
        "outs_over_hit": false
      },
      {
        "name": "MacKenzie Gore",
        "k_line": 5.5,
        "k_over_price": -143,
        "k_under_price": 122,
        "outs_line": 17.5,
        "outs_over_price": -128,
        "outs_under_price": -104,
        "actual_ks": 7,
        "actual_outs": 15,
        "k_over_hit": true,
        "outs_over_hit": false
      }
    ],
    "odds_recorded_at": "2026-07-01T20:35:37.289760+00:00",
    "odds_final": true,
    "away_score": 4,
    "home_score": 9,
    "total_runs": 13,
    "home_win": true,
    "over_hit": true,
    "away_f5_score": 1,
    "home_f5_score": 5,
    "f5_total_runs": 6,
    "f5_home_win": true,
    "f5_over_hit": true,
    "f5_spread_away_covered": false,
    "tt_away_over_hit": true,
    "tt_home_over_hit": true,
    "f5_tt_away_over_hit": false,
    "f5_tt_home_over_hit": true,
    "spread_away_covered": false,
    "annotated_at": "2026-07-01T20:37:29.238757+00:00"
  },
  {
    "date": "2026-07-01",
    "away": "Washington Nationals",
    "away_code": "WSN",
    "home": "Boston Red Sox",
    "home_code": "BOS",
    "game_time_utc": "2026-07-01T17:36:00Z",
    "away_pitcher": "Andrew Alvarez",
    "away_pitcher_hand": "L",
    "away_pitcher_id": "674841",
    "home_pitcher": "Payton Tolle",
    "home_pitcher_hand": "L",
    "home_pitcher_id": "801139",
    "ml_away": null,
    "ml_home": null,
    "spread_away_line": -7.5,
    "spread_away_price": -230,
    "spread_home_line": 7.5,
    "spread_home_price": 184,
    "total_line": 12.5,
    "over_price": 184,
    "under_price": -230,
    "f5_ml_away": 114,
    "f5_ml_home": -142,
    "f5_spread_away_line": 0.5,
    "f5_spread_away_price": -128,
    "f5_spread_home_line": -0.5,
    "f5_spread_home_price": -102,
    "f5_total_line": 4.5,
    "f5_over_price": -144,
    "f5_under_price": 110,
    "tt_away_line": 4.5,
    "tt_away_over_price": -105,
    "tt_away_under_price": -115,
    "tt_home_line": 5.5,
    "tt_home_over_price": 110,
    "tt_home_under_price": 114,
    "f5_tt_away_line": null,
    "f5_tt_away_over_price": null,
    "f5_tt_away_under_price": null,
    "f5_tt_home_line": null,
    "f5_tt_home_over_price": null,
    "f5_tt_home_under_price": null,
    "pitchers": [
      {
        "name": "Andrew Alvarez",
        "k_line": 4.5,
        "k_over_price": -108,
        "k_under_price": -114,
        "outs_line": 13.5,
        "outs_over_price": -108,
        "outs_under_price": -123,
        "actual_ks": null,
        "actual_outs": null,
        "k_over_hit": null,
        "outs_over_hit": null
      },
      {
        "name": "Payton Tolle",
        "k_line": 5.5,
        "k_over_price": -102,
        "k_under_price": -120,
        "outs_line": 17.5,
        "outs_over_price": -108,
        "outs_under_price": -105,
        "actual_ks": null,
        "actual_outs": null,
        "k_over_hit": null,
        "outs_over_hit": null
      }
    ],
    "odds_recorded_at": "2026-07-01T20:35:37.289760+00:00",
    "odds_final": true,
    "away_score": null,
    "home_score": null,
    "total_runs": null,
    "home_win": null,
    "over_hit": null,
    "away_f5_score": null,
    "home_f5_score": null,
    "f5_total_runs": null,
    "f5_home_win": null,
    "f5_over_hit": null,
    "f5_spread_away_covered": null,
    "tt_away_over_hit": null,
    "tt_home_over_hit": null,
    "f5_tt_away_over_hit": null,
    "f5_tt_home_over_hit": null,
    "spread_away_covered": null,
    "annotated_at": null
  },
  {
    "date": "2026-07-01",
    "away": "Detroit Tigers",
    "away_code": "DET",
    "home": "New York Yankees",
    "home_code": "NYY",
    "game_time_utc": "2026-07-01T17:36:00Z",
    "away_pitcher": "Troy Melton",
    "away_pitcher_hand": "R",
    "away_pitcher_id": "675512",
    "home_pitcher": "Will Warren",
    "home_pitcher_hand": "R",
    "home_pitcher_id": "701542",
    "ml_away": 120,
    "ml_home": -142,
    "spread_away_line": 1.5,
    "spread_away_price": -168,
    "spread_home_line": -1.5,
    "spread_home_price": 146,
    "total_line": 9.5,
    "over_price": -108,
    "under_price": -110,
    "f5_ml_away": 110,
    "f5_ml_home": -135,
    "f5_spread_away_line": 0.5,
    "f5_spread_away_price": -128,
    "f5_spread_home_line": -0.5,
    "f5_spread_home_price": -102,
    "f5_total_line": 5.5,
    "f5_over_price": 102,
    "f5_under_price": -132,
    "tt_away_line": 4.5,
    "tt_away_over_price": -104,
    "tt_away_under_price": -120,
    "tt_home_line": 4.5,
    "tt_home_over_price": -130,
    "tt_home_under_price": 105,
    "f5_tt_away_line": 2.5,
    "f5_tt_away_over_price": 105,
    "f5_tt_away_under_price": -135,
    "f5_tt_home_line": 2.5,
    "f5_tt_home_over_price": -120,
    "f5_tt_home_under_price": -110,
    "pitchers": [
      {
        "name": "Troy Melton",
        "k_line": 4.5,
        "k_over_price": -122,
        "k_under_price": -101,
        "outs_line": 16.5,
        "outs_over_price": -110,
        "outs_under_price": -117,
        "actual_ks": null,
        "actual_outs": null,
        "k_over_hit": null,
        "outs_over_hit": null
      },
      {
        "name": "Will Warren",
        "k_line": 5.5,
        "k_over_price": -115,
        "k_under_price": -104,
        "outs_line": 16.5,
        "outs_over_price": -104,
        "outs_under_price": -127,
        "actual_ks": null,
        "actual_outs": null,
        "k_over_hit": null,
        "outs_over_hit": null
      }
    ],
    "odds_recorded_at": "2026-07-01T14:56:04.272437+00:00",
    "odds_final": false,
    "away_score": null,
    "home_score": null,
    "total_runs": null,
    "home_win": null,
    "over_hit": null,
    "away_f5_score": null,
    "home_f5_score": null,
    "f5_total_runs": null,
    "f5_home_win": null,
    "f5_over_hit": null,
    "f5_spread_away_covered": null,
    "tt_away_over_hit": null,
    "tt_home_over_hit": null,
    "f5_tt_away_over_hit": null,
    "f5_tt_home_over_hit": null,
    "spread_away_covered": null,
    "annotated_at": null
  },
  {
    "date": "2026-07-01",
    "away": "Detroit Tigers",
    "away_code": "DET",
    "home": "New York Yankees",
    "home_code": "NYY",
    "game_time_utc": "2026-07-01T17:39:00Z",
    "away_pitcher": "Troy Melton",
    "away_pitcher_hand": "R",
    "away_pitcher_id": "675512",
    "home_pitcher": "Will Warren",
    "home_pitcher_hand": "R",
    "home_pitcher_id": "701542",
    "ml_away": -20000,
    "ml_home": 5000,
    "spread_away_line": -3.5,
    "spread_away_price": -424,
    "spread_home_line": 3.5,
    "spread_home_price": 320,
    "total_line": 8.5,
    "over_price": 291,
    "under_price": -186,
    "f5_ml_away": 114,
    "f5_ml_home": -142,
    "f5_spread_away_line": 0.5,
    "f5_spread_away_price": -125,
    "f5_spread_home_line": -0.5,
    "f5_spread_home_price": -104,
    "f5_total_line": 5.5,
    "f5_over_price": 104,
    "f5_under_price": -135,
    "tt_away_line": 4.5,
    "tt_away_over_price": -108,
    "tt_away_under_price": -118,
    "tt_home_line": 4.5,
    "tt_home_over_price": -138,
    "tt_home_under_price": 114,
    "f5_tt_away_line": null,
    "f5_tt_away_over_price": null,
    "f5_tt_away_under_price": null,
    "f5_tt_home_line": null,
    "f5_tt_home_over_price": null,
    "f5_tt_home_under_price": null,
    "pitchers": [
      {
        "name": "Troy Melton",
        "k_line": 4.5,
        "k_over_price": -125,
        "k_under_price": 118,
        "outs_line": 16.5,
        "outs_over_price": -104,
        "outs_under_price": -110,
        "actual_ks": null,
        "actual_outs": null,
        "k_over_hit": null,
        "outs_over_hit": null
      },
      {
        "name": "Will Warren",
        "k_line": 5.5,
        "k_over_price": -130,
        "k_under_price": 106,
        "outs_line": 16.5,
        "outs_over_price": -125,
        "outs_under_price": -105,
        "actual_ks": null,
        "actual_outs": null,
        "k_over_hit": null,
        "outs_over_hit": null
      }
    ],
    "odds_recorded_at": "2026-07-01T20:35:37.289760+00:00",
    "odds_final": true,
    "away_score": null,
    "home_score": null,
    "total_runs": null,
    "home_win": null,
    "over_hit": null,
    "away_f5_score": null,
    "home_f5_score": null,
    "f5_total_runs": null,
    "f5_home_win": null,
    "f5_over_hit": null,
    "f5_spread_away_covered": null,
    "tt_away_over_hit": null,
    "tt_home_over_hit": null,
    "f5_tt_away_over_hit": null,
    "f5_tt_home_over_hit": null,
    "spread_away_covered": null,
    "annotated_at": null
  },
  {
    "date": "2026-07-01",
    "away": "San Diego Padres",
    "away_code": "SDP",
    "home": "Chicago Cubs",
    "home_code": "CHC",
    "game_time_utc": "2026-07-01T18:21:00Z",
    "away_pitcher": "Walker Buehler",
    "away_pitcher_hand": "R",
    "away_pitcher_id": "621111",
    "home_pitcher": "Colin Rea",
    "home_pitcher_hand": "R",
    "home_pitcher_id": "607067",
    "ml_away": null,
    "ml_home": null,
    "spread_away_line": 10.5,
    "spread_away_price": 115,
    "spread_home_line": -13.5,
    "spread_home_price": 120,
    "total_line": 20.5,
    "over_price": -102,
    "under_price": 110,
    "f5_ml_away": -106,
    "f5_ml_home": -118,
    "f5_spread_away_line": 0.5,
    "f5_spread_away_price": -144,
    "f5_spread_home_line": -0.5,
    "f5_spread_home_price": 110,
    "f5_total_line": 6.5,
    "f5_over_price": -106,
    "f5_under_price": -122,
    "tt_away_line": 5.5,
    "tt_away_over_price": -120,
    "tt_away_under_price": 100,
    "tt_home_line": 5.5,
    "tt_home_over_price": -115,
    "tt_home_under_price": 105,
    "f5_tt_away_line": null,
    "f5_tt_away_over_price": null,
    "f5_tt_away_under_price": null,
    "f5_tt_home_line": null,
    "f5_tt_home_over_price": null,
    "f5_tt_home_under_price": null,
    "pitchers": [
      {
        "name": "Colin Rea",
        "k_line": 3.5,
        "k_over_price": -144,
        "k_under_price": 118,
        "outs_line": 15.5,
        "outs_over_price": 112,
        "outs_under_price": -144,
        "actual_ks": null,
        "actual_outs": null,
        "k_over_hit": null,
        "outs_over_hit": null
      },
      {
        "name": "Walker Buehler",
        "k_line": 3.5,
        "k_over_price": -147,
        "k_under_price": 134,
        "outs_line": 14.5,
        "outs_over_price": -152,
        "outs_under_price": 130,
        "actual_ks": null,
        "actual_outs": null,
        "k_over_hit": null,
        "outs_over_hit": null
      }
    ],
    "odds_recorded_at": "2026-07-01T20:35:37.289760+00:00",
    "odds_final": true,
    "away_score": null,
    "home_score": null,
    "total_runs": null,
    "home_win": null,
    "over_hit": null,
    "away_f5_score": null,
    "home_f5_score": null,
    "f5_total_runs": null,
    "f5_home_win": null,
    "f5_over_hit": null,
    "f5_spread_away_covered": null,
    "tt_away_over_hit": null,
    "tt_home_over_hit": null,
    "f5_tt_away_over_hit": null,
    "f5_tt_home_over_hit": null,
    "spread_away_covered": null,
    "annotated_at": null
  },
  {
    "date": "2026-07-01",
    "away": "New York Mets",
    "away_code": "NYM",
    "home": "Toronto Blue Jays",
    "home_code": "TOR",
    "game_time_utc": "2026-07-01T19:08:00Z",
    "away_pitcher": "Freddy Peralta",
    "away_pitcher_hand": "R",
    "away_pitcher_id": "642547",
    "home_pitcher": "Braydon Fisher",
    "home_pitcher_hand": "R",
    "home_pitcher_id": "680755",
    "ml_away": -114,
    "ml_home": -102,
    "spread_away_line": -1.5,
    "spread_away_price": 146,
    "spread_home_line": 1.5,
    "spread_home_price": -170,
    "total_line": 8.5,
    "over_price": -120,
    "under_price": 102,
    "f5_ml_away": -120,
    "f5_ml_home": -102,
    "f5_spread_away_line": -0.5,
    "f5_spread_away_price": 112,
    "f5_spread_home_line": 0.5,
    "f5_spread_home_price": -146,
    "f5_total_line": 4.5,
    "f5_over_price": -128,
    "f5_under_price": -102,
    "tt_away_line": 4.5,
    "tt_away_over_price": -104,
    "tt_away_under_price": -122,
    "tt_home_line": 4.5,
    "tt_home_over_price": 118,
    "tt_home_under_price": -145,
    "f5_tt_away_line": 2.5,
    "f5_tt_away_over_price": 110,
    "f5_tt_away_under_price": -140,
    "f5_tt_home_line": 2.5,
    "f5_tt_home_over_price": 120,
    "f5_tt_home_under_price": -154,
    "pitchers": [
      {
        "name": "Freddy Peralta",
        "k_line": 4.5,
        "k_over_price": -125,
        "k_under_price": 100,
        "outs_line": 17.5,
        "outs_over_price": -130,
        "outs_under_price": 110,
        "actual_ks": null,
        "actual_outs": null,
        "k_over_hit": null,
        "outs_over_hit": null
      }
    ],
    "odds_recorded_at": "2026-07-01T14:56:04.272437+00:00",
    "odds_final": false,
    "away_score": null,
    "home_score": null,
    "total_runs": null,
    "home_win": null,
    "over_hit": null,
    "away_f5_score": null,
    "home_f5_score": null,
    "f5_total_runs": null,
    "f5_home_win": null,
    "f5_over_hit": null,
    "f5_spread_away_covered": null,
    "tt_away_over_hit": null,
    "tt_home_over_hit": null,
    "f5_tt_away_over_hit": null,
    "f5_tt_home_over_hit": null,
    "spread_away_covered": null,
    "annotated_at": null
  },
  {
    "date": "2026-07-01",
    "away": "New York Mets",
    "away_code": "NYM",
    "home": "Toronto Blue Jays",
    "home_code": "TOR",
    "game_time_utc": "2026-07-01T19:28:00Z",
    "away_pitcher": "Freddy Peralta",
    "away_pitcher_hand": "R",
    "away_pitcher_id": "642547",
    "home_pitcher": "Spencer Miles",
    "home_pitcher_hand": "R",
    "home_pitcher_id": "693686",
    "ml_away": 1000,
    "ml_home": -1800,
    "spread_away_line": 4.5,
    "spread_away_price": 106,
    "spread_home_line": -4.5,
    "spread_home_price": -133,
    "total_line": 10.5,
    "over_price": -103,
    "under_price": -120,
    "f5_ml_away": -130,
    "f5_ml_home": 104,
    "f5_spread_away_line": -0.5,
    "f5_spread_away_price": 106,
    "f5_spread_home_line": 0.5,
    "f5_spread_home_price": -138,
    "f5_total_line": 4.5,
    "f5_over_price": -128,
    "f5_under_price": -102,
    "tt_away_line": 4.5,
    "tt_away_over_price": 100,
    "tt_away_under_price": -125,
    "tt_home_line": 4.5,
    "tt_home_over_price": 114,
    "tt_home_under_price": 120,
    "f5_tt_away_line": null,
    "f5_tt_away_over_price": null,
    "f5_tt_away_under_price": null,
    "f5_tt_home_line": null,
    "f5_tt_home_over_price": null,
    "f5_tt_home_under_price": null,
    "pitchers": [
      {
        "name": "Freddy Peralta",
        "k_line": 4.5,
        "k_over_price": -125,
        "k_under_price": 106,
        "outs_line": 17.5,
        "outs_over_price": -146,
        "outs_under_price": 110,
        "actual_ks": null,
        "actual_outs": null,
        "k_over_hit": null,
        "outs_over_hit": null
      }
    ],
    "odds_recorded_at": "2026-07-01T20:35:37.289760+00:00",
    "odds_final": true,
    "away_score": null,
    "home_score": null,
    "total_runs": null,
    "home_win": null,
    "over_hit": null,
    "away_f5_score": null,
    "home_f5_score": null,
    "f5_total_runs": null,
    "f5_home_win": null,
    "f5_over_hit": null,
    "f5_spread_away_covered": null,
    "tt_away_over_hit": null,
    "tt_home_over_hit": null,
    "f5_tt_away_over_hit": null,
    "f5_tt_home_over_hit": null,
    "spread_away_covered": null,
    "annotated_at": null
  },
  {
    "date": "2026-07-01",
    "away": "Pittsburgh Pirates",
    "away_code": "PIT",
    "home": "Philadelphia Phillies",
    "home_code": "PHI",
    "game_time_utc": "2026-07-01T22:41:00Z",
    "away_pitcher": "Paul Skenes",
    "away_pitcher_hand": "R",
    "away_pitcher_id": "694973",
    "home_pitcher": "Zack Wheeler",
    "home_pitcher_hand": "R",
    "home_pitcher_id": "554430",
    "ml_away": 120,
    "ml_home": -142,
    "spread_away_line": 1.5,
    "spread_away_price": -180,
    "spread_home_line": -1.5,
    "spread_home_price": 155,
    "total_line": 8.0,
    "over_price": -114,
    "under_price": -105,
    "f5_ml_away": 105,
    "f5_ml_home": -130,
    "f5_spread_away_line": 0.5,
    "f5_spread_away_price": -146,
    "f5_spread_home_line": -0.5,
    "f5_spread_home_price": 112,
    "f5_total_line": 3.5,
    "f5_over_price": -144,
    "f5_under_price": 110,
    "tt_away_line": 3.5,
    "tt_away_over_price": -122,
    "tt_away_under_price": -104,
    "tt_home_line": 4.5,
    "tt_home_over_price": 120,
    "tt_home_under_price": -135,
    "f5_tt_away_line": 1.5,
    "f5_tt_away_over_price": -120,
    "f5_tt_away_under_price": -110,
    "f5_tt_home_line": 1.5,
    "f5_tt_home_over_price": -140,
    "f5_tt_home_under_price": 110,
    "pitchers": [
      {
        "name": "Paul Skenes",
        "k_line": 7.5,
        "k_over_price": 119,
        "k_under_price": 116,
        "outs_line": 17.5,
        "outs_over_price": -162,
        "outs_under_price": 135,
        "actual_ks": null,
        "actual_outs": null,
        "k_over_hit": null,
        "outs_over_hit": null
      },
      {
        "name": "Zack Wheeler",
        "k_line": 7.5,
        "k_over_price": 110,
        "k_under_price": 134,
        "outs_line": 17.5,
        "outs_over_price": -186,
        "outs_under_price": 148,
        "actual_ks": null,
        "actual_outs": null,
        "k_over_hit": null,
        "outs_over_hit": null
      }
    ],
    "odds_recorded_at": "2026-07-01T20:35:37.289760+00:00",
    "odds_final": false,
    "away_score": null,
    "home_score": null,
    "total_runs": null,
    "home_win": null,
    "over_hit": null,
    "away_f5_score": null,
    "home_f5_score": null,
    "f5_total_runs": null,
    "f5_home_win": null,
    "f5_over_hit": null,
    "f5_spread_away_covered": null,
    "tt_away_over_hit": null,
    "tt_home_over_hit": null,
    "f5_tt_away_over_hit": null,
    "f5_tt_home_over_hit": null,
    "spread_away_covered": null,
    "annotated_at": null
  },
  {
    "date": "2026-07-01",
    "away": "St. Louis Cardinals",
    "away_code": "STL",
    "home": "Atlanta Braves",
    "home_code": "ATL",
    "game_time_utc": "2026-07-01T23:16:00Z",
    "away_pitcher": "Michael McGreevy",
    "away_pitcher_hand": "R",
    "away_pitcher_id": "700241",
    "home_pitcher": "Reynaldo Lopez",
    "home_pitcher_hand": "R",
    "home_pitcher_id": "625643",
    "ml_away": 117,
    "ml_home": -130,
    "spread_away_line": 1.5,
    "spread_away_price": -175,
    "spread_home_line": -1.5,
    "spread_home_price": 148,
    "total_line": 9.0,
    "over_price": -115,
    "under_price": -104,
    "f5_ml_away": -102,
    "f5_ml_home": -122,
    "f5_spread_away_line": 0.5,
    "f5_spread_away_price": -140,
    "f5_spread_home_line": -0.5,
    "f5_spread_home_price": 108,
    "f5_total_line": 4.5,
    "f5_over_price": -146,
    "f5_under_price": 112,
    "tt_away_line": 4.5,
    "tt_away_over_price": 112,
    "tt_away_under_price": -135,
    "tt_home_line": 4.5,
    "tt_home_over_price": -113,
    "tt_home_under_price": -110,
    "f5_tt_away_line": 2.5,
    "f5_tt_away_over_price": 105,
    "f5_tt_away_under_price": -135,
    "f5_tt_home_line": 2.5,
    "f5_tt_home_over_price": -105,
    "f5_tt_home_under_price": -125,
    "pitchers": [
      {
        "name": "Michael McGreevy",
        "k_line": 3.5,
        "k_over_price": 128,
        "k_under_price": -152,
        "outs_line": 17.5,
        "outs_over_price": 116,
        "outs_under_price": 100,
        "actual_ks": null,
        "actual_outs": null,
        "k_over_hit": null,
        "outs_over_hit": null
      },
      {
        "name": "Reynaldo Lopez",
        "k_line": 3.5,
        "k_over_price": 130,
        "k_under_price": -152,
        "outs_line": null,
        "outs_over_price": null,
        "outs_under_price": null,
        "actual_ks": null,
        "actual_outs": null,
        "k_over_hit": null,
        "outs_over_hit": null
      }
    ],
    "odds_recorded_at": "2026-07-01T20:35:37.289760+00:00",
    "odds_final": false,
    "away_score": null,
    "home_score": null,
    "total_runs": null,
    "home_win": null,
    "over_hit": null,
    "away_f5_score": null,
    "home_f5_score": null,
    "f5_total_runs": null,
    "f5_home_win": null,
    "f5_over_hit": null,
    "f5_spread_away_covered": null,
    "tt_away_over_hit": null,
    "tt_home_over_hit": null,
    "f5_tt_away_over_hit": null,
    "f5_tt_home_over_hit": null,
    "spread_away_covered": null,
    "annotated_at": null
  },
  {
    "date": "2026-07-01",
    "away": "Tampa Bay Rays",
    "away_code": "TBR",
    "home": "Kansas City Royals",
    "home_code": "KCR",
    "game_time_utc": "2026-07-01T23:41:00Z",
    "away_pitcher": "Shane McClanahan",
    "away_pitcher_hand": "L",
    "away_pitcher_id": "663556",
    "home_pitcher": "Seth Lugo",
    "home_pitcher_hand": "R",
    "home_pitcher_id": "607625",
    "ml_away": -134,
    "ml_home": 120,
    "spread_away_line": -1.5,
    "spread_away_price": 110,
    "spread_home_line": 1.5,
    "spread_home_price": -130,
    "total_line": 10.5,
    "over_price": -108,
    "under_price": -109,
    "f5_ml_away": -140,
    "f5_ml_home": 112,
    "f5_spread_away_line": -0.5,
    "f5_spread_away_price": -106,
    "f5_spread_home_line": 0.5,
    "f5_spread_home_price": -122,
    "f5_total_line": 5.5,
    "f5_over_price": -106,
    "f5_under_price": -122,
    "tt_away_line": 5.5,
    "tt_away_over_price": -111,
    "tt_away_under_price": -115,
    "tt_home_line": 4.5,
    "tt_home_over_price": -115,
    "tt_home_under_price": -110,
    "f5_tt_away_line": 2.5,
    "f5_tt_away_over_price": -125,
    "f5_tt_away_under_price": -105,
    "f5_tt_home_line": 2.5,
    "f5_tt_home_over_price": 105,
    "f5_tt_home_under_price": -135,
    "pitchers": [
      {
        "name": "Seth Lugo",
        "k_line": 3.5,
        "k_over_price": -134,
        "k_under_price": 122,
        "outs_line": 16.5,
        "outs_over_price": -104,
        "outs_under_price": 102,
        "actual_ks": null,
        "actual_outs": null,
        "k_over_hit": null,
        "outs_over_hit": null
      },
      {
        "name": "Shane McClanahan",
        "k_line": 4.5,
        "k_over_price": 106,
        "k_under_price": -121,
        "outs_line": 15.5,
        "outs_over_price": 128,
        "outs_under_price": -167,
        "actual_ks": null,
        "actual_outs": null,
        "k_over_hit": null,
        "outs_over_hit": null
      }
    ],
    "odds_recorded_at": "2026-07-01T20:35:37.289760+00:00",
    "odds_final": false,
    "away_score": null,
    "home_score": null,
    "total_runs": null,
    "home_win": null,
    "over_hit": null,
    "away_f5_score": null,
    "home_f5_score": null,
    "f5_total_runs": null,
    "f5_home_win": null,
    "f5_over_hit": null,
    "f5_spread_away_covered": null,
    "tt_away_over_hit": null,
    "tt_home_over_hit": null,
    "f5_tt_away_over_hit": null,
    "f5_tt_home_over_hit": null,
    "spread_away_covered": null,
    "annotated_at": null
  },
  {
    "date": "2026-07-01",
    "away": "Cincinnati Reds",
    "away_code": "CIN",
    "home": "Milwaukee Brewers",
    "home_code": "MIL",
    "game_time_utc": "2026-07-02T00:11:00Z",
    "away_pitcher": "Andrew Abbott",
    "away_pitcher_hand": "L",
    "away_pitcher_id": "671096",
    "home_pitcher": "Shane Drohan",
    "home_pitcher_hand": "L",
    "home_pitcher_id": "675660",
    "ml_away": 136,
    "ml_home": -162,
    "spread_away_line": 1.5,
    "spread_away_price": -154,
    "spread_home_line": -1.5,
    "spread_home_price": 130,
    "total_line": 9.0,
    "over_price": -105,
    "under_price": -110,
    "f5_ml_away": 126,
    "f5_ml_home": -154,
    "f5_spread_away_line": 0.5,
    "f5_spread_away_price": -114,
    "f5_spread_home_line": -0.5,
    "f5_spread_home_price": -114,
    "f5_total_line": 4.5,
    "f5_over_price": -140,
    "f5_under_price": 108,
    "tt_away_line": 3.5,
    "tt_away_over_price": -135,
    "tt_away_under_price": 108,
    "tt_home_line": 4.5,
    "tt_home_over_price": -120,
    "tt_home_under_price": -105,
    "f5_tt_away_line": 2.5,
    "f5_tt_away_over_price": 124,
    "f5_tt_away_under_price": -160,
    "f5_tt_home_line": 2.5,
    "f5_tt_home_over_price": -110,
    "f5_tt_home_under_price": -120,
    "pitchers": [
      {
        "name": "Andrew Abbott",
        "k_line": 4.5,
        "k_over_price": 132,
        "k_under_price": -156,
        "outs_line": 16.5,
        "outs_over_price": -104,
        "outs_under_price": -125,
        "actual_ks": null,
        "actual_outs": null,
        "k_over_hit": null,
        "outs_over_hit": null
      },
      {
        "name": "Shane Drohan",
        "k_line": 5.5,
        "k_over_price": 115,
        "k_under_price": 144,
        "outs_line": 14.5,
        "outs_over_price": -135,
        "outs_under_price": 124,
        "actual_ks": null,
        "actual_outs": null,
        "k_over_hit": null,
        "outs_over_hit": null
      }
    ],
    "odds_recorded_at": "2026-07-01T20:35:37.289760+00:00",
    "odds_final": false,
    "away_score": null,
    "home_score": null,
    "total_runs": null,
    "home_win": null,
    "over_hit": null,
    "away_f5_score": null,
    "home_f5_score": null,
    "f5_total_runs": null,
    "f5_home_win": null,
    "f5_over_hit": null,
    "f5_spread_away_covered": null,
    "tt_away_over_hit": null,
    "tt_home_over_hit": null,
    "f5_tt_away_over_hit": null,
    "f5_tt_home_over_hit": null,
    "spread_away_covered": null,
    "annotated_at": null
  },
  {
    "date": "2026-07-01",
    "away": "Minnesota Twins",
    "away_code": "MIN",
    "home": "Houston Astros",
    "home_code": "HOU",
    "game_time_utc": "2026-07-02T00:11:00Z",
    "away_pitcher": "Taj Bradley",
    "away_pitcher_hand": "R",
    "away_pitcher_id": "671737",
    "home_pitcher": "Tatsuya Imai",
    "home_pitcher_hand": "R",
    "home_pitcher_id": "837227",
    "ml_away": 120,
    "ml_home": -138,
    "spread_away_line": 1.5,
    "spread_away_price": -181,
    "spread_home_line": -1.5,
    "spread_home_price": 158,
    "total_line": 8.5,
    "over_price": -108,
    "under_price": -110,
    "f5_ml_away": 106,
    "f5_ml_home": -132,
    "f5_spread_away_line": 0.5,
    "f5_spread_away_price": -140,
    "f5_spread_home_line": -0.5,
    "f5_spread_home_price": 108,
    "f5_total_line": 4.5,
    "f5_over_price": -110,
    "f5_under_price": -118,
    "tt_away_line": 3.5,
    "tt_away_over_price": -135,
    "tt_away_under_price": 106,
    "tt_home_line": 4.5,
    "tt_home_over_price": 112,
    "tt_home_under_price": -135,
    "f5_tt_away_line": 1.5,
    "f5_tt_away_over_price": -140,
    "f5_tt_away_under_price": 110,
    "f5_tt_home_line": 2.5,
    "f5_tt_home_over_price": 120,
    "f5_tt_home_under_price": -154,
    "pitchers": [
      {
        "name": "Taj Bradley",
        "k_line": 5.5,
        "k_over_price": -136,
        "k_under_price": 106,
        "outs_line": 17.5,
        "outs_over_price": -102,
        "outs_under_price": -130,
        "actual_ks": null,
        "actual_outs": null,
        "k_over_hit": null,
        "outs_over_hit": null
      },
      {
        "name": "Tatsuya Imai",
        "k_line": 6.5,
        "k_over_price": 118,
        "k_under_price": 120,
        "outs_line": 16.5,
        "outs_over_price": 100,
        "outs_under_price": -128,
        "actual_ks": null,
        "actual_outs": null,
        "k_over_hit": null,
        "outs_over_hit": null
      }
    ],
    "odds_recorded_at": "2026-07-01T20:35:37.289760+00:00",
    "odds_final": false,
    "away_score": null,
    "home_score": null,
    "total_runs": null,
    "home_win": null,
    "over_hit": null,
    "away_f5_score": null,
    "home_f5_score": null,
    "f5_total_runs": null,
    "f5_home_win": null,
    "f5_over_hit": null,
    "f5_spread_away_covered": null,
    "tt_away_over_hit": null,
    "tt_home_over_hit": null,
    "f5_tt_away_over_hit": null,
    "f5_tt_home_over_hit": null,
    "spread_away_covered": null,
    "annotated_at": null
  },
  {
    "date": "2026-07-01",
    "away": "Miami Marlins",
    "away_code": "MIA",
    "home": "Colorado Rockies",
    "home_code": "COL",
    "game_time_utc": "2026-07-02T00:41:00Z",
    "away_pitcher": "Max Meyer",
    "away_pitcher_hand": "R",
    "away_pitcher_id": "676974",
    "home_pitcher": "Kyle Freeland",
    "home_pitcher_hand": "L",
    "home_pitcher_id": "607536",
    "ml_away": -154,
    "ml_home": 130,
    "spread_away_line": -1.5,
    "spread_away_price": -108,
    "spread_home_line": 1.5,
    "spread_home_price": -110,
    "total_line": 11.0,
    "over_price": -104,
    "under_price": -114,
    "f5_ml_away": -158,
    "f5_ml_home": 126,
    "f5_spread_away_line": -0.5,
    "f5_spread_away_price": -118,
    "f5_spread_home_line": 0.5,
    "f5_spread_home_price": -110,
    "f5_total_line": 5.5,
    "f5_over_price": -128,
    "f5_under_price": -102,
    "tt_away_line": 5.5,
    "tt_away_over_price": -130,
    "tt_away_under_price": 105,
    "tt_home_line": 4.5,
    "tt_home_over_price": -113,
    "tt_home_under_price": -110,
    "f5_tt_away_line": 2.5,
    "f5_tt_away_over_price": -154,
    "f5_tt_away_under_price": 120,
    "f5_tt_home_line": 2.5,
    "f5_tt_home_over_price": 100,
    "f5_tt_home_under_price": -130,
    "pitchers": [
      {
        "name": "Kyle Freeland",
        "k_line": 3.5,
        "k_over_price": -140,
        "k_under_price": 120,
        "outs_line": 15.5,
        "outs_over_price": -130,
        "outs_under_price": -102,
        "actual_ks": null,
        "actual_outs": null,
        "k_over_hit": null,
        "outs_over_hit": null
      },
      {
        "name": "Max Meyer",
        "k_line": 5.5,
        "k_over_price": -138,
        "k_under_price": 117,
        "outs_line": 17.5,
        "outs_over_price": -130,
        "outs_under_price": 100,
        "actual_ks": null,
        "actual_outs": null,
        "k_over_hit": null,
        "outs_over_hit": null
      }
    ],
    "odds_recorded_at": "2026-07-01T20:35:37.289760+00:00",
    "odds_final": false,
    "away_score": null,
    "home_score": null,
    "total_runs": null,
    "home_win": null,
    "over_hit": null,
    "away_f5_score": null,
    "home_f5_score": null,
    "f5_total_runs": null,
    "f5_home_win": null,
    "f5_over_hit": null,
    "f5_spread_away_covered": null,
    "tt_away_over_hit": null,
    "tt_home_over_hit": null,
    "f5_tt_away_over_hit": null,
    "f5_tt_home_over_hit": null,
    "spread_away_covered": null,
    "annotated_at": null
  },
  {
    "date": "2026-07-01",
    "away": "San Francisco Giants",
    "away_code": "SFG",
    "home": "Arizona Diamondbacks",
    "home_code": "ARI",
    "game_time_utc": "2026-07-02T01:41:00Z",
    "away_pitcher": "Trevor McDonald",
    "away_pitcher_hand": "R",
    "away_pitcher_id": "686790",
    "home_pitcher": "Zac Gallen",
    "home_pitcher_hand": "R",
    "home_pitcher_id": "668678",
    "ml_away": 110,
    "ml_home": -125,
    "spread_away_line": 1.5,
    "spread_away_price": -180,
    "spread_home_line": -1.5,
    "spread_home_price": 155,
    "total_line": 9.5,
    "over_price": -105,
    "under_price": -114,
    "f5_ml_away": 100,
    "f5_ml_home": -120,
    "f5_spread_away_line": 0.5,
    "f5_spread_away_price": -140,
    "f5_spread_home_line": -0.5,
    "f5_spread_home_price": 108,
    "f5_total_line": 5.5,
    "f5_over_price": 104,
    "f5_under_price": -135,
    "tt_away_line": 4.5,
    "tt_away_over_price": -108,
    "tt_away_under_price": -115,
    "tt_home_line": 4.5,
    "tt_home_over_price": -122,
    "tt_home_under_price": 100,
    "f5_tt_away_line": 2.5,
    "f5_tt_away_over_price": 100,
    "f5_tt_away_under_price": -130,
    "f5_tt_home_line": 2.5,
    "f5_tt_home_over_price": -110,
    "f5_tt_home_under_price": -120,
    "pitchers": [
      {
        "name": "Trevor McDonald",
        "k_line": 3.5,
        "k_over_price": 102,
        "k_under_price": -128,
        "outs_line": 15.5,
        "outs_over_price": 122,
        "outs_under_price": -162,
        "actual_ks": null,
        "actual_outs": null,
        "k_over_hit": null,
        "outs_over_hit": null
      },
      {
        "name": "Zac Gallen",
        "k_line": 3.5,
        "k_over_price": -110,
        "k_under_price": -105,
        "outs_line": 17.5,
        "outs_over_price": 100,
        "outs_under_price": 106,
        "actual_ks": null,
        "actual_outs": null,
        "k_over_hit": null,
        "outs_over_hit": null
      }
    ],
    "odds_recorded_at": "2026-07-01T20:35:37.289760+00:00",
    "odds_final": false,
    "away_score": null,
    "home_score": null,
    "total_runs": null,
    "home_win": null,
    "over_hit": null,
    "away_f5_score": null,
    "home_f5_score": null,
    "f5_total_runs": null,
    "f5_home_win": null,
    "f5_over_hit": null,
    "f5_spread_away_covered": null,
    "tt_away_over_hit": null,
    "tt_home_over_hit": null,
    "f5_tt_away_over_hit": null,
    "f5_tt_home_over_hit": null,
    "spread_away_covered": null,
    "annotated_at": null
  },
  {
    "date": "2026-07-01",
    "away": "Los Angeles Dodgers",
    "away_code": "LAD",
    "home": "Athletics",
    "home_code": "ATH",
    "game_time_utc": "2026-07-02T01:41:00Z",
    "away_pitcher": "Charlie Barnes",
    "away_pitcher_hand": "L",
    "away_pitcher_id": "656212",
    "home_pitcher": "J.T. Ginn",
    "home_pitcher_hand": "R",
    "home_pitcher_id": "669372",
    "ml_away": -162,
    "ml_home": 141,
    "spread_away_line": -1.5,
    "spread_away_price": -110,
    "spread_home_line": 1.5,
    "spread_home_price": -107,
    "total_line": 11.0,
    "over_price": -104,
    "under_price": -110,
    "f5_ml_away": -148,
    "f5_ml_home": 124,
    "f5_spread_away_line": -0.5,
    "f5_spread_away_price": -113,
    "f5_spread_home_line": 0.5,
    "f5_spread_home_price": -115,
    "f5_total_line": 5.5,
    "f5_over_price": -130,
    "f5_under_price": 100,
    "tt_away_line": 6.5,
    "tt_away_over_price": 105,
    "tt_away_under_price": 106,
    "tt_home_line": 4.5,
    "tt_home_over_price": 100,
    "tt_home_under_price": -111,
    "f5_tt_away_line": 3.5,
    "f5_tt_away_over_price": 114,
    "f5_tt_away_under_price": -145,
    "f5_tt_home_line": 2.5,
    "f5_tt_home_over_price": -105,
    "f5_tt_home_under_price": -125,
    "pitchers": [
      {
        "name": "JT Ginn",
        "k_line": 4.5,
        "k_over_price": 105,
        "k_under_price": -124,
        "outs_line": 15.5,
        "outs_over_price": 115,
        "outs_under_price": 125,
        "actual_ks": null,
        "actual_outs": null,
        "k_over_hit": null,
        "outs_over_hit": null
      }
    ],
    "odds_recorded_at": "2026-07-01T20:35:37.289760+00:00",
    "odds_final": false,
    "away_score": null,
    "home_score": null,
    "total_runs": null,
    "home_win": null,
    "over_hit": null,
    "away_f5_score": null,
    "home_f5_score": null,
    "f5_total_runs": null,
    "f5_home_win": null,
    "f5_over_hit": null,
    "f5_spread_away_covered": null,
    "tt_away_over_hit": null,
    "tt_home_over_hit": null,
    "f5_tt_away_over_hit": null,
    "f5_tt_home_over_hit": null,
    "spread_away_covered": null,
    "annotated_at": null
  },
  {
    "date": "2026-07-01",
    "away": "Pittsburgh Pirates",
    "away_code": "PIT",
    "home": "Philadelphia Phillies",
    "home_code": "PHI",
    "game_time_utc": "2026-07-02T16:36:00Z",
    "away_pitcher": "Paul Skenes",
    "away_pitcher_hand": "R",
    "away_pitcher_id": "694973",
    "home_pitcher": "Zack Wheeler",
    "home_pitcher_hand": "R",
    "home_pitcher_id": "554430",
    "ml_away": 110,
    "ml_home": -126,
    "spread_away_line": 1.5,
    "spread_away_price": -190,
    "spread_home_line": -1.5,
    "spread_home_price": 162,
    "total_line": 10.5,
    "over_price": 104,
    "under_price": 102,
    "f5_ml_away": null,
    "f5_ml_home": null,
    "f5_spread_away_line": null,
    "f5_spread_away_price": null,
    "f5_spread_home_line": null,
    "f5_spread_home_price": null,
    "f5_total_line": null,
    "f5_over_price": null,
    "f5_under_price": null,
    "tt_away_line": null,
    "tt_away_over_price": null,
    "tt_away_under_price": null,
    "tt_home_line": null,
    "tt_home_over_price": null,
    "tt_home_under_price": null,
    "f5_tt_away_line": null,
    "f5_tt_away_over_price": null,
    "f5_tt_away_under_price": null,
    "f5_tt_home_line": null,
    "f5_tt_home_over_price": null,
    "f5_tt_home_under_price": null,
    "pitchers": [],
    "odds_recorded_at": "2026-07-01T20:35:37.289760+00:00",
    "odds_final": false,
    "away_score": null,
    "home_score": null,
    "total_runs": null,
    "home_win": null,
    "over_hit": null,
    "away_f5_score": null,
    "home_f5_score": null,
    "f5_total_runs": null,
    "f5_home_win": null,
    "f5_over_hit": null,
    "f5_spread_away_covered": null,
    "tt_away_over_hit": null,
    "tt_home_over_hit": null,
    "f5_tt_away_over_hit": null,
    "f5_tt_home_over_hit": null,
    "spread_away_covered": null,
    "annotated_at": null
  },
  {
    "date": "2026-07-01",
    "away": "Cincinnati Reds",
    "away_code": "CIN",
    "home": "Milwaukee Brewers",
    "home_code": "MIL",
    "game_time_utc": "2026-07-02T18:11:00Z",
    "away_pitcher": "Andrew Abbott",
    "away_pitcher_hand": "L",
    "away_pitcher_id": "671096",
    "home_pitcher": "Shane Drohan",
    "home_pitcher_hand": "L",
    "home_pitcher_id": "675660",
    "ml_away": 165,
    "ml_home": -190,
    "spread_away_line": 1.5,
    "spread_away_price": -140,
    "spread_home_line": -1.5,
    "spread_home_price": 130,
    "total_line": 7.0,
    "over_price": 100,
    "under_price": 104,
    "f5_ml_away": null,
    "f5_ml_home": null,
    "f5_spread_away_line": null,
    "f5_spread_away_price": null,
    "f5_spread_home_line": null,
    "f5_spread_home_price": null,
    "f5_total_line": null,
    "f5_over_price": null,
    "f5_under_price": null,
    "tt_away_line": null,
    "tt_away_over_price": null,
    "tt_away_under_price": null,
    "tt_home_line": null,
    "tt_home_over_price": null,
    "tt_home_under_price": null,
    "f5_tt_away_line": null,
    "f5_tt_away_over_price": null,
    "f5_tt_away_under_price": null,
    "f5_tt_home_line": null,
    "f5_tt_home_over_price": null,
    "f5_tt_home_under_price": null,
    "pitchers": [],
    "odds_recorded_at": "2026-07-01T20:35:37.289760+00:00",
    "odds_final": false,
    "away_score": null,
    "home_score": null,
    "total_runs": null,
    "home_win": null,
    "over_hit": null,
    "away_f5_score": null,
    "home_f5_score": null,
    "f5_total_runs": null,
    "f5_home_win": null,
    "f5_over_hit": null,
    "f5_spread_away_covered": null,
    "tt_away_over_hit": null,
    "tt_home_over_hit": null,
    "f5_tt_away_over_hit": null,
    "f5_tt_home_over_hit": null,
    "spread_away_covered": null,
    "annotated_at": null
  },
  {
    "date": "2026-07-01",
    "away": "Chicago White Sox",
    "away_code": "CHW",
    "home": "Cleveland Guardians",
    "home_code": "CLE",
    "game_time_utc": "2026-07-02T22:41:00Z",
    "away_pitcher": "Noah Schultz",
    "away_pitcher_hand": "L",
    "away_pitcher_id": "702273",
    "home_pitcher": "Joey Cantillo",
    "home_pitcher_hand": "L",
    "home_pitcher_id": "676282",
    "ml_away": -120,
    "ml_home": 104,
    "spread_away_line": -1.5,
    "spread_away_price": 140,
    "spread_home_line": 1.5,
    "spread_home_price": -155,
    "total_line": 8.5,
    "over_price": -106,
    "under_price": -105,
    "f5_ml_away": null,
    "f5_ml_home": null,
    "f5_spread_away_line": null,
    "f5_spread_away_price": null,
    "f5_spread_home_line": null,
    "f5_spread_home_price": null,
    "f5_total_line": null,
    "f5_over_price": null,
    "f5_under_price": null,
    "tt_away_line": null,
    "tt_away_over_price": null,
    "tt_away_under_price": null,
    "tt_home_line": null,
    "tt_home_over_price": null,
    "tt_home_under_price": null,
    "f5_tt_away_line": null,
    "f5_tt_away_over_price": null,
    "f5_tt_away_under_price": null,
    "f5_tt_home_line": null,
    "f5_tt_home_over_price": null,
    "f5_tt_home_under_price": null,
    "pitchers": [],
    "odds_recorded_at": "2026-07-01T20:35:37.289760+00:00",
    "odds_final": false,
    "away_score": null,
    "home_score": null,
    "total_runs": null,
    "home_win": null,
    "over_hit": null,
    "away_f5_score": null,
    "home_f5_score": null,
    "f5_total_runs": null,
    "f5_home_win": null,
    "f5_over_hit": null,
    "f5_spread_away_covered": null,
    "tt_away_over_hit": null,
    "tt_home_over_hit": null,
    "f5_tt_away_over_hit": null,
    "f5_tt_home_over_hit": null,
    "spread_away_covered": null,
    "annotated_at": null
  },
  {
    "date": "2026-07-01",
    "away": "Detroit Tigers",
    "away_code": "DET",
    "home": "Texas Rangers",
    "home_code": "TEX",
    "game_time_utc": "2026-07-03T00:06:00Z",
    "away_pitcher": "Troy Melton",
    "away_pitcher_hand": "R",
    "away_pitcher_id": "675512",
    "home_pitcher": "MacKenzie Gore",
    "home_pitcher_hand": "L",
    "home_pitcher_id": "669022",
    "ml_away": 116,
    "ml_home": -130,
    "spread_away_line": 1.5,
    "spread_away_price": -190,
    "spread_home_line": -1.5,
    "spread_home_price": 172,
    "total_line": 8.0,
    "over_price": -104,
    "under_price": -110,
    "f5_ml_away": null,
    "f5_ml_home": null,
    "f5_spread_away_line": null,
    "f5_spread_away_price": null,
    "f5_spread_home_line": null,
    "f5_spread_home_price": null,
    "f5_total_line": null,
    "f5_over_price": null,
    "f5_under_price": null,
    "tt_away_line": null,
    "tt_away_over_price": null,
    "tt_away_under_price": null,
    "tt_home_line": null,
    "tt_home_over_price": null,
    "tt_home_under_price": null,
    "f5_tt_away_line": null,
    "f5_tt_away_over_price": null,
    "f5_tt_away_under_price": null,
    "f5_tt_home_line": null,
    "f5_tt_home_over_price": null,
    "f5_tt_home_under_price": null,
    "pitchers": [],
    "odds_recorded_at": "2026-07-01T20:35:37.289760+00:00",
    "odds_final": false,
    "away_score": null,
    "home_score": null,
    "total_runs": null,
    "home_win": null,
    "over_hit": null,
    "away_f5_score": null,
    "home_f5_score": null,
    "f5_total_runs": null,
    "f5_home_win": null,
    "f5_over_hit": null,
    "f5_spread_away_covered": null,
    "tt_away_over_hit": null,
    "tt_home_over_hit": null,
    "f5_tt_away_over_hit": null,
    "f5_tt_home_over_hit": null,
    "spread_away_covered": null,
    "annotated_at": null
  },
  {
    "date": "2026-07-01",
    "away": "Los Angeles Angels",
    "away_code": "LAA",
    "home": "Seattle Mariners",
    "home_code": "SEA",
    "game_time_utc": "2026-07-03T01:41:00Z",
    "away_pitcher": "TBD",
    "away_pitcher_hand": "",
    "away_pitcher_id": null,
    "home_pitcher": "TBD",
    "home_pitcher_hand": "",
    "home_pitcher_id": null,
    "ml_away": 176,
    "ml_home": -205,
    "spread_away_line": 1.5,
    "spread_away_price": -125,
    "spread_home_line": -1.5,
    "spread_home_price": 108,
    "total_line": 7.5,
    "over_price": -110,
    "under_price": -110,
    "f5_ml_away": null,
    "f5_ml_home": null,
    "f5_spread_away_line": null,
    "f5_spread_away_price": null,
    "f5_spread_home_line": null,
    "f5_spread_home_price": null,
    "f5_total_line": null,
    "f5_over_price": null,
    "f5_under_price": null,
    "tt_away_line": null,
    "tt_away_over_price": null,
    "tt_away_under_price": null,
    "tt_home_line": null,
    "tt_home_over_price": null,
    "tt_home_under_price": null,
    "f5_tt_away_line": null,
    "f5_tt_away_over_price": null,
    "f5_tt_away_under_price": null,
    "f5_tt_home_line": null,
    "f5_tt_home_over_price": null,
    "f5_tt_home_under_price": null,
    "pitchers": [],
    "odds_recorded_at": "2026-07-01T20:35:37.289760+00:00",
    "odds_final": false,
    "away_score": null,
    "home_score": null,
    "total_runs": null,
    "home_win": null,
    "over_hit": null,
    "away_f5_score": null,
    "home_f5_score": null,
    "f5_total_runs": null,
    "f5_home_win": null,
    "f5_over_hit": null,
    "f5_spread_away_covered": null,
    "tt_away_over_hit": null,
    "tt_home_over_hit": null,
    "f5_tt_away_over_hit": null,
    "f5_tt_home_over_hit": null,
    "spread_away_covered": null,
    "annotated_at": null
  }
]